<?xml version="1.0" encoding="UTF-8" standalone="yes"?>
<yml_catalog date="2023-02-25 16:11">
  <shop>
    <name>Интернет-магазин "AVEON" - товары для всей семьи! Самые низкие цены!</name>
    <company>Интернет-магазин "AVEON" - товары для всей семьи! Самые низкие цены!</company>
    <url>https://aveon.net.ua/</url>
    <currencies>
      <currency id="USD" rate="CB"/>
      <currency id="UAH" rate="1"/>
      <currency id="BYN" rate="CB"/>
      <currency id="KZT" rate="CB"/>
      <currency id="EUR" rate="CB"/>
    </currencies>
    <categories>
      <category id="30014688">Красота и здоровье</category>
      <category id="30017035">Автотовары, электроинструмент, ручной инструмент</category>
      <category id="30017047">Спорт, здоровье, туризм</category>
      <category id="30018536">Электроника</category>
      <category id="30017053">Товары для дома и сада</category>
      <category id="30017064">Детский мир, детские товары</category>
      <category id="82325193">Кресла-мешки, кресла-груши</category>
      <category id="86247596">Электроника</category>
      <category id="88376566">Электроника</category>
      <category id="70180736">Колонки и акустические системы</category>
      <category id="70173138">Товары для животных</category>
      <category id="70180949">PowerBank, внешние аккумуляторы</category>
      <category id="70181491">Фонари, прожекторы, светильники</category>
      <category id="70182026">Наушники и гарнитура</category>
      <category id="71610854">Кулеры для воды</category>
      <category id="63744367">Чехлы / Стекла на Apple iPhone</category>
      <category id="30018858">Все для кухни</category>
      <category id="64032704">Чемоданы / Сумки</category>
      <category id="92670183">Всё для кухни</category>
      <category id="86247595">Спорт, фитнес, туризм</category>
      <category id="99320587">Подарки и сувениры</category>
      <category id="99406043">Одежда и обувь</category>
      <category id="109460283">Парфюмерия. Женские и Мужские духи</category>
      <category id="98559707">Спорт, здоровье, туризм</category>
      <category id="101985757">Новогодний товар</category>
      <category id="108784467">Постельное белье ,полотенца</category>
      <category id="108442227">Красота и здоровье</category>
      <category id="108442228" parentId="108442227">Косметика декоративная, уход за телом</category>
      <category id="108852295">Подарки и сувениры</category>
      <category id="108482107">Уценка</category>
      <category id="108495070">Парфюмированые спреи Victoria's Secret</category>
      <category id="110446915">Косметика BILOU , вся продукция нашумевшего Немецкого бренда,ОРИГИНАЛ !</category>
      <category id="109015942">Пижамы, нижнее белье, халаты</category>
      <category id="108117197">Мужская обувь</category>
      <category id="108118382">Женская обувь</category>
    </categories>
    <offers>
      <offer id="905112762" available="true">
        <url>https://aveon.net.ua/p905112762-power-bank-powerbank.html</url>
        <oldprice>663</oldprice>
        <price>363</price>
        <currencyId>UAH</currencyId>
        <categoryId>70180949</categoryId>
        <picture>https://images.prom.ua/1853485518_power-bank-powerbank.jpg</picture>
        <picture>https://images.prom.ua/1853485519_power-bank-powerbank.jpg</picture>
        <picture>https://images.prom.ua/1853485520_power-bank-powerbank.jpg</picture>
        <picture>https://images.prom.ua/1853485521_power-bank-powerbank.jpg</picture>
        <picture>https://images.prom.ua/1853485522_power-bank-powerbank.jpg</picture>
        <picture>https://images.prom.ua/1853485523_power-bank-powerbank.jpg</picture>
        <picture>https://images.prom.ua/1853485524_power-bank-powerbank.jpg</picture>
        <pickup>false</pickup>
        <delivery>true</delivery>
        <name>Power Bank powerbank 50000 mAh Solar LED | Повер Банк LED | Портативное зарядное устройство | Пауэр Солар</name>
        <vendorCode>905112762</vendorCode>
        <description><![CDATA[Power Bank 50000 с солнечной батареей - внешний аккумулятор, надежный источник питания, который станет хорошим другом для путешественников, деловых и активных людей. Говорите по телефону, слушайте музыку, играйте, фотографируйте и снимайте больше с помощью Power Bank 50000. 

Solar 50000mAh Power Bank выручит в критической ситуации и значительно продлить время автономной работы ваших любимых девайсов: смартфонов, плееров, планшетов, фотоаппаратов и прочих устройств. Специальные индикаторы, размещенные на лицевой панели, оповестят об оставшемся уровне заряда.



Портативный аккумулятор 50000 - это уникальное устройство, которое позволит вашему телефону или планшету работать дольше. Power Bank не займет много места в рюкзаке или сумке, а его наличие позволит подзарядить смартфон в любом удобном месте.



На батарее есть яркий LED диод. Корпус Power Bank хорошо защищен от падения. Так же есть защита от попадания влаги, но погружать полностью в воду не рекомендуется.

В режиме резервного аккумулятора Вы можете накопить заряд от сети, а после подзарядить плеер или мобильный телефон. В комплекте с зарядным устройством поставляются кабель зарядки USB-microUSB. На портативном зарядном устройстве имеется два разъема USB для зарядки техники и разъем miniUSB для зарядки самого Power Bank, разъемы надежно закрываются резиновыми крышками и не боятся попадания влаги.

 

Универсальное устройство работающее от сети, ПК и энергии солнца. Это зарядное устройство с 50000 mAh для Iphone, планшетных ПК и USB устройств на 500 циклов подзарядки в течение срока службы батареи.

Устройство имеет индикатор, который отображает точный процент питания. Двойной USB DC 5 В/1a выход для зарядки мобильных телефонов, SB DC 5 В/2.1a Выход заряда для планшета. Ультра высокая эффективность преобразования (&gt; 75%). Время полной зарядки аккумулятора (переменного тока): 7-8 часов. ABS + PC дизайн корпуса обеспечивает эффект анти-царапин и анти-отпечатков пальцев.

 

Характеристики:

Выходное напряжение: DC 5 В

2 порт Выходной ток: 1000mA/2000mA макс

Входное напряжение/ток: 5.0 В/1000mA

Солнечные фотоэлектрические панели: 5.5 В 300mA 1.5 Вт

USB кабель для зарядки: 1 шт

Размер: 132 * 76 * 21 мм

Вес: около 202 г

 

 

 
]]></description>
      </offer>
      <offer id="968479237" available="true">
        <url>https://aveon.net.ua/p968479237-samaya-bolshaya-jbl.html</url>
        <oldprice>1169</oldprice>
        <price>1019</price>
        <currencyId>UAH</currencyId>
        <categoryId>70180736</categoryId>
        <picture>https://images.prom.ua/1853500105_samaya-bolshaya-jbl.jpg</picture>
        <picture>https://images.prom.ua/1853500106_samaya-bolshaya-jbl.jpg</picture>
        <picture>https://images.prom.ua/1853500107_samaya-bolshaya-jbl.jpg</picture>
        <picture>https://images.prom.ua/1853500108_samaya-bolshaya-jbl.jpg</picture>
        <picture>https://images.prom.ua/1853500109_samaya-bolshaya-jbl.jpg</picture>
        <picture>https://images.prom.ua/1853500110_samaya-bolshaya-jbl.jpg</picture>
        <picture>https://images.prom.ua/1853500111_samaya-bolshaya-jbl.jpg</picture>
        <picture>https://images.prom.ua/1853500112_samaya-bolshaya-jbl.jpg</picture>
        <picture>https://images.prom.ua/1853500113_samaya-bolshaya-jbl.jpg</picture>
        <picture>https://images.prom.ua/1853500114_samaya-bolshaya-jbl.jpg</picture>
        <pickup>false</pickup>
        <delivery>true</delivery>
        <name>Самая БОЛЬШАЯ JBL Xtreme BIG EXTREME мощная портативная блютуз колонка</name>
        <vendorCode>968479237</vendorCode>
        <description>Самая БОЛЬШАЯ JBL Xtreme BIG EXTREME мощная портативная блютуз колонка!



Представляем Вашему вниманию одну из лучших беспроводных портативных колонок JBL XTREME BIG (28 см). 

Самый мощный звук и бас! Внешний вид привлечет любое внимание!



У нас каждая колонка проверена и протестирована!

В случае возникновения каких-либо проблемных вопросов возврат денег и оплату транспортных перевозок берем на себя.



JBL XTREME большая - самая мощная акустика в линейке JBL, размер колонки оригинальный, не Xtreme mini.

JBL XTREME – это полнофункциональный портативный Bluetooth-динамик, который легко воспроизводит потрясающе мощный стереозвук через четыре активных преобразователя и два видимых излучателя низких частот JBL.

JBL XTREME оснащен емким перезаряжаемый литий-ионный аккумулятором на 10 000 мА*ч, обеспечивающим до 8 -10 часов автономной работы, и двойным USB-выходом для зарядки, поэтому ваша музыка будет звучать, а устройства – работать так долго, сколько вам нужно.

Корпус JBL XTREME изготовлен из прорезиненного пластика с тканевой обшивкой, которая успешно защищает от брызг и дождя.

JBL XTREME оснащен спикерфоном с функциями шумоподавления и эхокомпенсации для четкой конференц-связи, а функция JBL Connect позволяет объединять в беспроводную сеть несколько колонок, поддерживающих эту функцию, и таким образом усиливать акустические ощущения от прослушивания.
ЛУЧШЕЕ ПРЕДЛОЖЕНИЕ В УКРАИНЕ JBL XTREME BIG (28 см)!!! Качество класса ААА. Незаменимая вещь на любой вечеринке или отдыхе на природе. Также в наличии имеются Charge 2, 3, 4, Flip 3, 4, Xtreme Mini (23 см), Boombox (Big 28, 34 см, Mini), Pulse 3, 5.



Колонка JBL XTREME SUPERBASS 

• Чистый и мощный звук

• Батарея 10000 mAh

• Время прослушивания до 8-10 часов

• Герметический корпус с защитой от воды

• Подключение с помощью Bluetooth к любому устройству, включая планшеты и телефоны.

• Возможность сопряжения 2-х колонок

• FM радио

• Воспроизведение с флешки USB, microSD



ХАРАКТЕРИСТИКИ

• Номинальная мощность: 2*20 Вт с двойным усилением

• Коэффициент "сигнал-шум" 80 дб 

• Питание: от батарей, от USB.

• Время работы: до 10 часов.

• Функции: встроенный микрофон.

• Бас: 2 пассивных излучателя.



ГАБАРИТЫ:

• Ш*В*Г 283*126*122

• вес 2112 грамм



Комплектация: 

• акустическая система JBL XTREME;

• кабель Micro-USB;

• кабель AUX;

• ремень для ношения через плечо.</description>
        <param name="Поддерживаемые беспроводные интерфейсы">Bluetooth</param>
        <param name="Состояние">Новое</param>
        <param name="Формат акустики">Стерео</param>
        <param name="Тип питания">Аккумулятор</param>
        <param name="Поддерживаемые карты памяти">microSD</param>
        <param name="Суммарная мощность звука" unit="Вт">6</param>
        <param name="Особенности">Зарядка плеера/смартфона|FM-приемник</param>
        <param name="Цвет корпуса" unit="">На выбор</param>
      </offer>
      <offer id="1038921486" available="true">
        <url>https://aveon.net.ua/p1038921486-kamera-video-nablyudenie.html</url>
        <oldprice>2925</oldprice>
        <price>1425</price>
        <currencyId>UAH</currencyId>
        <categoryId>30018536</categoryId>
        <picture>https://images.prom.ua/1970674779_ip-kamera-video-nablyudenie.jpg</picture>
        <picture>https://images.prom.ua/1970689773_ip-kamera-video-nablyudenie.jpg</picture>
        <picture>https://images.prom.ua/1970674780_ip-kamera-video-nablyudenie.jpg</picture>
        <picture>https://images.prom.ua/1970689774_ip-kamera-video-nablyudenie.jpg</picture>
        <picture>https://images.prom.ua/1970689775_ip-kamera-video-nablyudenie.jpg</picture>
        <picture>https://images.prom.ua/1970689776_ip-kamera-video-nablyudenie.jpg</picture>
        <picture>https://images.prom.ua/1970689781_ip-kamera-video-nablyudenie.jpg</picture>
        <picture>https://images.prom.ua/1970674778_ip-kamera-video-nablyudenie.jpg</picture>
        <pickup>false</pickup>
        <delivery>true</delivery>
        <name>IP Камера видео-наблюдение IP 163E, WI-FI камера, онлайн поворотная, ночное видение</name>
        <vendor>IP</vendor>
        <vendorCode>1038921486</vendorCode>
        <description>IP-Камера это еще один способ уберечь себя от непрошеных гостей. Используя данный девайс вы сможете с любой точки мира наблюдать за своим имуществом онлайн. Все что от вас нужно - это постоянный интернет и скачанное приложение на ваше мобильное устройство . Камеры с углом обзора 360 с помощью поворотного механизма.

Особенности:


	инфракрасный светодиод, который позволяет снимать ночью на расстоянии до 10 метров
	благодаря приложению Mi Home для смартфонов на платформах как Android, так и iOS, и соединению Wi-Fi вы можете преодолеть расстояние и увидеть, что происходит у вас дома
	имеет широкоугольный объектив 
	в комплекте микрофон и динамик
	облачное хранение (вы можете использовать карту памяти до 64 Гб или воспользоваться непосредственно записью в облачное хранение) 
	дистанционное управление поворотом по двум осям


Технические характеристики:


	Тип: IP- камера видеонаблюдения
	Тип корпуса: купольная камера
	Исполнение: поворотная
	Инфракрасный датчик: есть
	Угол обзора: 90°
	Мощность: 5 Вт
	Расстояние: 10 м
	Аудио: микрофон и динамик
	Разрешение: 720P HD
	Дополнительно: датчик движения, сигнализация


Комплектация:


	Камера IP;
	Кронштейн;
	Адаптер и шнур для подключения;
	Инструкция;
	Упаковка. 

</description>
        <param name="Кронштейн в комплекте">Да</param>
        <param name="Изображение картинки" unit="">Цветная</param>
        <param name="Режим съемки &quot;День/ночь&quot;" unit="">True</param>
        <param name="Тип матрицы" unit="">CMOS</param>
        <param name="Наличие ИК-подсветки&#x9;" unit="">Да</param>
        <param name="Дальность ИК-подсветки&#x9;" unit="">25 м</param>
      </offer>
      <offer id="1174843503" available="true">
        <url>https://aveon.net.ua/p1174843503-robot-pylesos-akkumulyatornyj.html</url>
        <oldprice>600</oldprice>
        <price>450</price>
        <currencyId>UAH</currencyId>
        <categoryId>30017053</categoryId>
        <picture>https://images.prom.ua/2362783118_robot-pylesos-akkumulyatornyj.jpg</picture>
        <picture>https://images.prom.ua/2362783150_robot-pylesos-akkumulyatornyj.jpg</picture>
        <picture>https://images.prom.ua/2362783156_robot-pylesos-akkumulyatornyj.jpg</picture>
        <picture>https://images.prom.ua/2362783155_robot-pylesos-akkumulyatornyj.jpg</picture>
        <picture>https://images.prom.ua/2362783117_robot-pylesos-akkumulyatornyj.jpg</picture>
        <picture>https://images.prom.ua/2362783123_robot-pylesos-akkumulyatornyj.jpg</picture>
        <picture>https://images.prom.ua/2362783131_robot-pylesos-akkumulyatornyj.jpg</picture>
        <picture>https://images.prom.ua/2362783145_robot-pylesos-akkumulyatornyj.jpg</picture>
        <picture>https://images.prom.ua/2362783149_robot-pylesos-akkumulyatornyj.jpg</picture>
        <picture>https://images.prom.ua/2362783154_robot-pylesos-akkumulyatornyj.jpg</picture>
        <pickup>false</pickup>
        <delivery>true</delivery>
        <name>Робот Пылесос аккумуляторный умный Ximei Smart Robot на аккумуляторе 18650 заряд от USB</name>
        <vendorCode>1174843503</vendorCode>
        <country_of_origin>Китай</country_of_origin>
        <description>Умный Робот пылесос XIMEI Smart Robot, 1500 Вт

Робот-пылесос способен производить уборку дома без Вашей помощи.

Все, что нужно для начала работы, это включить интеллектуальный прибор и запустить Пылесос автоматически подстраивается под любое напольное покрытие, будь то кафельная плитка, паркет, линолеум

Наличие «Виртуальной стены» поможет сделать уборку более безопасной.

Достаточно поставить датчик в нужном месте и пылесос не пересечет границу убираемого помещения.

Единственное, что Вам нужно сделать, это высыпать мусор из контейнера-пыле сборника.

Данный представитель роботизированной бытовой техники способен на многое:


	Убирает вдвое большую территорию за один цикл благодаря увеличенному объему мусоросборника на одинаковой мощности;
	Является универсальным устройством, благодаря которому участие человека в процессе уборки дома сводится к минимуму: робот-пылесос XIMEI соберет весь мусор
	Максимально эффективно очищает до 150-ти квадратов поверхности за один раз. При чем роботу все равно на каком полу работать, будь то ламинат, паркетная доска, линолеум либо длинноворсовый ковер


Характеристики:

Тип оборудования: робот пылесос

Марка: Ximei

Диаметр/толщина: 23 см / 6 см

Напряжение: 6В

Турбо щетка: есть

Материал производства: пластик

Срок автономной работы: 2 часа

Объем пылесборника: 0,6 - 1 л

Шумность: не более 50 дБ

Объем аккумуляторной батареи: 1200 мАч

Страна-изготовитель: Китай

Комплектация:

Робот пылесос Ximei smart robot 14+

USB зарядка

Инструкция 

Упаковка: коробка
</description>
        <param name="Цвет корпуса">Черный</param>
        <param name="Тип аккумулятора">Li-Ion</param>
        <param name="Тип">Робот</param>
        <param name="Состояние">Новое</param>
      </offer>
      <offer id="1247484595" available="true">
        <url>https://aveon.net.ua/p1247484595-umnye-smart-chasy.html</url>
        <oldprice>660</oldprice>
        <price>465</price>
        <currencyId>UAH</currencyId>
        <categoryId>30018536</categoryId>
        <picture>https://images.prom.ua/2579969286_umnye-smart-chasy-telefon.jpg</picture>
        <picture>https://images.prom.ua/2579969262_umnye-smart-chasy-telefon.jpg</picture>
        <picture>https://images.prom.ua/2579969261_umnye-smart-chasy-telefon.jpg</picture>
        <picture>https://images.prom.ua/2579969278_umnye-smart-chasy-telefon.jpg</picture>
        <picture>https://images.prom.ua/2579969250_umnye-smart-chasy-telefon.jpg</picture>
        <picture>https://images.prom.ua/2579969276_umnye-smart-chasy-telefon.jpg</picture>
        <picture>https://images.prom.ua/2579969283_umnye-smart-chasy-telefon.jpg</picture>
        <pickup>false</pickup>
        <delivery>true</delivery>
        <name>Умные Смарт часы-телефон Smart Watch X6</name>
        <vendorCode>1247484595</vendorCode>
        <description>Смарт часы Х6 обладают рядом неоспоримых достоинств, выгодно отличающих их от аналогов. Аккумуляторная батарея увеличенной емкости, позволяет использовать гаджет смарт вотч X6 до двух дней в активном режиме и семи – в режиме ожидания, без дополнительной подзарядки. Форма корпуса в виде изогнутой кривой, позволяет удобно разместить девайс на руке пользователя, а наличие нескольких видов циферблата, дает возможность выбрать его в соответствии с личными предпочтениями обладателя этой модели. Отличительными чертами данной модели смарт часов, являются: Стильный дизайн, несомненно притягивающий взоры окружающих. Чувствительный сенсорный экран. Современные комплектующие последнего поколения. Наличие большого количества дополнительных функций. К тому же, часы Smart Watch X6 подойдут для руки любого размера.Мощный процессор обеспечивает быстродействие часов, а качество воспроизведения фото и музыкальных файлов, гарантирует сенсорный экран с высокой степенью разрешения. Корпус прочный, выполнен из сплава металлов, защищает от влаги и механических повреждений. Ремешок выполнен из гипераллергенного силикона также черного цвета. Наличие Bluetooth позволяет синхронизировать часы Smart Watch X6 со смартфоном, что значительно расширяет их возможности. Для работы с внешним устройством используется приложение BT Notification Наличие СИМ карты, превращает умные часы в полноценный телефон, обладающий всеми, ему присущими функциями (прием вызовов и совершение звонков и СМС сообщений). Большое количество различных основных и дополнительных функций позволяет использовать SmartWatch Х6 в различных жизненных ситуациях (контроль сна и активности, напоминание и счетчик калорий). Наличие камеры позволяет делать снимки, а функция anti-lost обеспечит сохранность умных часов, подав сигнал на сопряженный с ними смартфон, в случае удаления гаджета на расстояние более 10,0 метров от пользователя. Работая с синхронизированным телефоном, можно управлять его камерой.</description>
        <param name="Тип">Умные часы</param>
        <param name="Совместимость с">IOS|Android</param>
        <param name="Состояние">Новое</param>
        <param name="Цвет" unit="">На выбор</param>
      </offer>
      <offer id="1294600828" available="true">
        <url>https://aveon.net.ua/p1294600828-nochnik-silikonovyj-panda.html</url>
        <oldprice>728</oldprice>
        <price>578</price>
        <currencyId>UAH</currencyId>
        <categoryId>30017053</categoryId>
        <picture>https://images.prom.ua/2729622236_nochnik-silikonovyj-panda.jpg</picture>
        <picture>https://images.prom.ua/2729622216_nochnik-silikonovyj-panda.jpg</picture>
        <picture>https://images.prom.ua/2729622229_nochnik-silikonovyj-panda.jpg</picture>
        <picture>https://images.prom.ua/2729622235_nochnik-silikonovyj-panda.jpg</picture>
        <picture>https://images.prom.ua/2729622238_nochnik-silikonovyj-panda.jpg</picture>
        <pickup>false</pickup>
        <delivery>true</delivery>
        <name>Ночник силиконовый Панда LOSSO LJC-142-А (открытые глаза)</name>
        <vendorCode>1294600828</vendorCode>
        <description>Силиконовый светильник "Панда" –  оригинальный ночник, который сможет украсить не только детскую спальню, но и замечательно впишется в интерьер любой комнаты. Мягким, приглушенным светом лампа в виде китайского мишки панды окутает детскую комнату волшебным приятным светом, подарив детям море радости и чувство защищенности. С таким чудесным светящимся другом и сказочным персонажем ребенку будет совсем не страшно засыпать ночью.

Лампа ночник Панда разработана специально для тактильного "общения" с силиконовым животным. Его можно взять в руки, помять, прислонить к телу, принести в кровать и просто поставить рядом. И это не просто силиконовый ночник, это - замечательная игрушка для ребенка, с которой он может не расставаться и днем, и ночью. Через пару дней они станут неразлучными друзьями, а родители будут наслаждаться тишиной вечернего времяпровождения и только выключать мишку после того, как ребенок спокойно уснет.

Панда Losso - это светодиодный ночник со всеми цветами радуги. Этот милый сенсорный ночник имеет 2 режима работы. Нажав кнопку включения с нижней стороны, светильник начнет светится тёплым белым светом. При легком хлопке по макушке Панды, он начнет изменять цвет по кругу каждые 3 секунды и будет работать в таком режиме до следующего хлопка. Второй хлопок фиксирует цвет - Панда будет светится в одном свете до следующего - третьего хлопка. Последний - выключит лампу. А дальше все сначала.

Лед ночник Панда имеет ряд преимуществ:


	свет не имеет бликов и не слепит глаза;
	приятный мягкий свет абсолютно не мешает сну;
	лампа - не нагревается - малыш не обожжется;
	ночник мягкий и приятный на ощупь;
	имеет встроенную батарею и заряжается от USB;
	абсолютно безопасен для здоровья;
	плафон изготовлен из гипоаллергенного силикона;
	не имеет запаха


Силиконовый светильник Панда поставляется в двух вариантах: с открытыми и закрытыми глазами. Выберите тот, который будет по душе Вам и Вашему ребенку.

Детский мягкий ночник Панда имеет встроенную батарею, емкостью 1200 мАч, которая способна длительное время поддерживать свечение лампы. Зарядить батарею можно через USB кабель, который идет в комплекте с ночником.

Характеристики:


	Цвет:  белый
	Размер:   106*112*136 мм
	Материал:   Силикон, Пластик
	Напряжение: 5В, 1000мА
	Мощность: 1,5 Вт
	Емкость батареи: 1200 мАч (модель 8650)
	Вес: 300 г

</description>
        <param name="Состояние">Новое</param>
        <param name="Тип" unit="">Светильник</param>
        <param name="Цвет" unit="">Несколько режимов</param>
      </offer>
      <offer id="1332513579" available="true">
        <url>https://aveon.net.ua/p1332513579-vozdushnyj-stajler-dlya.html</url>
        <oldprice>1155</oldprice>
        <price>1005</price>
        <currencyId>UAH</currencyId>
        <categoryId>30018536</categoryId>
        <picture>https://images.prom.ua/2851317538_vozdushnyj-stajler-dlya.jpg</picture>
        <picture>https://images.prom.ua/2851319864_vozdushnyj-stajler-dlya.jpg</picture>
        <picture>https://images.prom.ua/2851319863_vozdushnyj-stajler-dlya.jpg</picture>
        <picture>https://images.prom.ua/2851317539_vozdushnyj-stajler-dlya.jpg</picture>
        <pickup>false</pickup>
        <delivery>true</delivery>
        <name>Воздушный стайлер для волос 7 в 1 Gemei GM4836</name>
        <vendorCode>1332513579</vendorCode>
        <country_of_origin>Китай</country_of_origin>
        <description>Воздушный стайлер для волос 7 в 1 Gemei GM4836

Великолепный комплексный уход за Вашими волосами - это 7 в 1 стайлер для волос Gemei GM 4836! Вы сможете моделировать различные прически благодаря 9 насадкам к воздушному стайлеру. Такой прибор подойдет как опытному парикмахеру, так и для домашнего использования. 

Стайлер похож на плойку, но имеет 9 насадок:: концентратор, насадка для объема, расческа для выпрямления, щипцы для завивки, утюжок, конусная насадка и три круглых расчески. Вы сможете делать крупные и мелкие, горизонтальные и спиральные локоны, ретро-локоны, а также придавать дополнительный объем. Если у вас нет времени для укладки, на этот случай предусмотрены специальные насадки для кудрявых или вьющихся волос, которые обеспечивают их быстрое распутывание и выпрямление. Немаловажной дополнительной функцией есть ионизация, которая препятствует «намагничиванию» волос и придает дополнительный блеск.

Воздушный стайлер для волос 7 в 1 Gemei GM 4836 — это незаменимый прибор, который должен присутствовать в инвентаре каждой девушки и женщины.

ТЕХНИЧЕСКИЕ ХАРАКТЕРИСТИКИ


	Производитель: Gemei;
	Модель: GM 4836;
	Тип: набор для укладки;
	Мощность:1200 ВТ
	Защита от перегрева: да;
	Количество скоростей: 2;
	Температурный режим: 3;
	Тип питания: сеть 220 В;
	Насадки: 6 шт.;


Комплект:

Концентратор 9,5 - 3,6 см

Подъемник для объема 12,5 - 6 см

Расческа для выпрямления 14,8 - 5 см

Две круглых расчески для больших кудрей 17,5 - 4,5 см, для маленьких 18 - 2,5 см

Щипцы для завивки 20,3 - 2 см
</description>
        <param name="Терморегулятор">Да</param>
        <param name="Состояние">Новое</param>
      </offer>
      <offer id="1457663380" available="true">
        <url>https://aveon.net.ua/p1457663380-uvlazhnitel-vozduha-ultrazvukovoj.html</url>
        <oldprice>389</oldprice>
        <price>239</price>
        <currencyId>UAH</currencyId>
        <categoryId>30017053</categoryId>
        <picture>https://images.prom.ua/3262309393_uvlazhnitel-vozduha-ultrazvukovoj.jpg</picture>
        <picture>https://images.prom.ua/3262309397_uvlazhnitel-vozduha-ultrazvukovoj.jpg</picture>
        <picture>https://images.prom.ua/3262309394_uvlazhnitel-vozduha-ultrazvukovoj.jpg</picture>
        <picture>https://images.prom.ua/3262309398_uvlazhnitel-vozduha-ultrazvukovoj.jpg</picture>
        <picture>https://images.prom.ua/3262309396_uvlazhnitel-vozduha-ultrazvukovoj.jpg</picture>
        <picture>https://images.prom.ua/3262309395_uvlazhnitel-vozduha-ultrazvukovoj.jpg</picture>
        <pickup>false</pickup>
        <delivery>true</delivery>
        <name>Увлажнитель воздуха ультразвуковой Humidifier EL-544-23</name>
        <vendorCode>1457663380</vendorCode>
        <country_of_origin>Китай</country_of_origin>
        <description>Ультразвуковой увлажнитель воздуха Humidifier - просто необходимая вещь в каждом доме, где есть ребенок, он поможет создать оптимальный микроклимат и обеспечит необходимую влажность в помещении, а разноцветная подсветка создаст приятную и комфортную атмосферу и поможет ребенку быстрее заснуть. Особенно в отопительный сезон, когда воздух в доме сухой.

Одним из неоспоримым плюсов данного увлажнителя воздуха является наличие на верхней части девайса стандартного Usb входа, который закрыт стильной силиконовой заглушкой. Через него можно подзаряжать гаджеты или подключить любое Usb устройство.

Если вы хотите, чтобы вас всегда сопровождал приятный аромат- то увлажнитель Humidifier для Вас!

Увлажнитель можно использовать:

- Как дома, так и находясь на работе в офисе, торговом центре, где всегда сухой воздух и нашей коже и легким не хватает увлажнения.

- В машине он будет увлажнять воздух в салоне автомобиля а, при добавлении эфирных масел, может использоваться для ароматерапии. Главный плюс такой ароматизации, то что она натуральна и полезна для нашего организма.

- Можно использовать в отопительный период во время сна, в качестве персонального увлажнителя.

- В вечернее и ночное время может служить ночником благодаря приятной подсветке.

- В период болезни детей, им нужен влажный и чистый воздух - увлажнитель вам поможет в этом - поставьте увлажнитель на тумбочку возле кроватки ребёнка или в изголовье.

Увлажнитель воздуха Humidifier – отличный выбор в сегменте портативных мини-увлажнителей воздуха и ароматизаторов с лаконичным дизайном и достойным функционалом. 

 

Комплектация: увлажнитель, кабель, упаковка.
</description>
        <param name="Применение прибора">Для дома, квартиры</param>
        <param name="Тип управления">Сенсорное</param>
        <param name="Тип">Увлажнитель</param>
        <param name="Состояние">Новое</param>
        <param name="Ночной режим работы">Да</param>
        <param name="Автоотключение при отсутствии воды">Да</param>
        <param name="Тип питания">Сеть 220 В</param>
        <param name="Подсветка">Да</param>
        <param name="Материал корпуса">Пластик</param>
      </offer>
      <offer id="1522562776" available="true">
        <url>https://aveon.net.ua/p1522562776-letayuschij-shar-spinner.html</url>
        <oldprice>435</oldprice>
        <price>285</price>
        <currencyId>UAH</currencyId>
        <categoryId>30017064</categoryId>
        <picture>https://images.prom.ua/3473679660_letayuschij-shar-spinner.jpg</picture>
        <picture>https://images.prom.ua/3473679662_letayuschij-shar-spinner.jpg</picture>
        <picture>https://images.prom.ua/3473679659_letayuschij-shar-spinner.jpg</picture>
        <picture>https://images.prom.ua/3473680352_letayuschij-shar-spinner.jpg</picture>
        <picture>https://images.prom.ua/3473680336_letayuschij-shar-spinner.jpg</picture>
        <picture>https://images.prom.ua/3473680348_letayuschij-shar-spinner.jpg</picture>
        <picture>https://images.prom.ua/3473680365_letayuschij-shar-spinner.jpg</picture>
        <pickup>false</pickup>
        <delivery>true</delivery>
        <name>Летающий шар спиннер светящийся FlyNova pro Gyrosphere Игрушка мяч бумеранг для ребёнка</name>
        <vendorCode>1522562776</vendorCode>
        <description>Летающий шар - это очень увлекательная и инновационная игрушка для всех возрастов, которая подарит море впечатлений и настоящее удовольствие не только ребенку, но и взрослому. 

Особенности и преимущества: 


	Игрушка развивает быстроту реакции, ловкость и внимание, а также координацию движений вашего ребенка.
	Два винта — шестилопастный и трехлопастный, вращающийся в противоположном направлении относительно основного.
	По внутренней части натянута лента с яркими RGB светодиодами. Во время работы шар переливается разными цветами и выглядит очень красиво.
	Заряда аккумулятора хватает примерно до 10 минут работы.
	Заряжается шар 25-30 мин.
	Материал сферической оболочки достаточно гибкий и упругий, благодаря чему, шару не страшны падения.


Функции:


	Запускается шар встряхиванием его рукой.
	Наклонив летающий шар назад и слегка вверх, бросьте его, и он волшебным образом вернется в вашу руку, как бумеранг.
	Наклонив летающий шар вперёд, бросьте его и он полетит прямо.
	Держа шар ровно, подбросьте его вверх, шар взлетит и плавно опустится.
	Запустив шар и положив его на ладонь, и он может левитировать в руке.
	Чтобы остановить шар, необходимо его перевернуть и встряхнуть.


Характеристики:


	Заряд от USB шнура;
	Время зарядки: около 25 минут;
	Продолжительность работы: до 10 минут;
	Диаметр шара: 95 мм;
	Вес: 27 г;
	Вес упаковки: 170 г;
	Размер упаковки: 100х100х100 мм.


Комплектация:


	Летающий шар;
	Фирменная упаковка;
	USB-кабель;
	 Руководство пользователя.

</description>
      </offer>
      <offer id="1547468671" available="true">
        <url>https://aveon.net.ua/p1547468671-minidinamik-bluetooth-kms.html</url>
        <oldprice>555</oldprice>
        <price>405</price>
        <currencyId>UAH</currencyId>
        <categoryId>70180736</categoryId>
        <picture>https://images.prom.ua/3553497181_minidinamik-bluetooth-kms-k12.jpg</picture>
        <picture>https://images.prom.ua/3553497180_minidinamik-bluetooth-kms-k12.jpg</picture>
        <picture>https://images.prom.ua/3553497182_minidinamik-bluetooth-kms-k12.jpg</picture>
        <pickup>false</pickup>
        <delivery>true</delivery>
        <name>Минидинамик Bluetooth KMS-K12</name>
        <vendor>Kimiso</vendor>
        <vendorCode>1547468671</vendorCode>
        <country_of_origin>Китай</country_of_origin>
        <description>

Цветной RGB светодиодный светильник



Поочередно излучают разноцветные огоньки, что привлекательно в темное время суток. Усиливают атмосферу просмотра при прослушивании музыки или просмотре фильмов и игр.



Двойной будильник



Можно установить одновременно два будильника, на разное время, что подходит для вашего графика. По вашему выбору включите звуковой сигнал или радио.



Hi-fi стерео



Встроенный динамик 3 Вт полного диапазона с басовой диафрагмой, технология DSP приносит удивительную четкость и качество звучания, позволяют наслаждаться всеми деталями музыки.



Светодиодный автоматический сенсорный экран



При движении в пределах 4 метров перед колонкой, экран автоматически включится. Выключение автоматическое через 10 секунд.



Длительное время работы в режиме ожидания



Встроенный аккумулятор высокой емкости 2000 мАч, поддержка воспроизведения музыки до 18 часов.



Блютуз 5,0



Встроенный чип Bluetooth 5,0, Автоматическое сопряжение при включении, расстояние подключения более 10 метров,



Совместим со всеми устройствами bluetooth.



Компактный размер



Колонка маленькая, не занимает много места, удобна для транспортировки.



FM радио



Встроенная функция FM-радио позволяет выбирать из широкого спектра бесплатных станций для прослушивания музыки, новостей, ток-шоу и т. д.







Громкая связь



Вы можете легко принять вызов в доме или офисе, в любом месте во время подключения к вашему смартфону.



Поддержка SD/TF карт



Поддержка TF-карты plug and play, поддержка до 32G.



Простое управление кнопками



Вы можете нажать кнопки для включения/выключения, воспроизведения/паузы, переключения режима, пропуска песен, регулировки громкости и т. д.



Параметры:



Версия Bluetooth: 5,0

Встроенное напряжение: 3,7 в

Частотный диапазон: 150 Гц-20 кГц

Режим воспроизведения: Bluetooth, AUX, TF-карты, FM

Размер: 85*85 мм

Отношение сигнал-шум: ≥ 90 дБ

Емкость аккумулятора: 2000 мАч

Напряжение зарядки: 5 В/500 мА

Время воспроизведения: 12-18 ч



Комплектация:



1 X Bluetooth-колонка

1 X USB-кабель для зарядки

1 X Инструкция по эксплуатации</description>
        <param name="Интерфейсы">USB|jack 3.5 мм</param>
        <param name="Тип питания">Аккумулятор|USB-порт</param>
        <param name="Поддерживаемые беспроводные интерфейсы">Bluetooth</param>
        <param name="Поддерживаемые карты памяти">TF Card</param>
        <param name="Особенности">FM-приемник</param>
        <param name="Состояние">Новое</param>
      </offer>
      <offer id="1626010180" available="true">
        <url>https://aveon.net.ua/p1626010180-akkumulyatornaya-mashinka-trimer.html</url>
        <oldprice>771</oldprice>
        <price>621</price>
        <currencyId>UAH</currencyId>
        <categoryId>30014688</categoryId>
        <picture>https://images.prom.ua/3811626996_akkumulyatornaya-mashinka-trimer.jpg</picture>
        <picture>https://images.prom.ua/3811627139_akkumulyatornaya-mashinka-trimer.jpg</picture>
        <picture>https://images.prom.ua/3811627138_akkumulyatornaya-mashinka-trimer.jpg</picture>
        <picture>https://images.prom.ua/3811627141_akkumulyatornaya-mashinka-trimer.jpg</picture>
        <picture>https://images.prom.ua/3811627140_akkumulyatornaya-mashinka-trimer.jpg</picture>
        <picture>https://images.prom.ua/3811627184_akkumulyatornaya-mashinka-trimer.jpg</picture>
        <picture>https://images.prom.ua/3811627183_akkumulyatornaya-mashinka-trimer.jpg</picture>
        <picture>https://images.prom.ua/3811627162_akkumulyatornaya-mashinka-trimer.jpg</picture>
        <picture>https://images.prom.ua/3811627185_akkumulyatornaya-mashinka-trimer.jpg</picture>
        <picture>https://images.prom.ua/3811627188_akkumulyatornaya-mashinka-trimer.jpg</picture>
        <pickup>false</pickup>
        <delivery>true</delivery>
        <name>Аккумуляторная машинка тример для стрижки 3 насадки керамические лезвия USB стрижка VGR V-090</name>
        <vendor>VGR</vendor>
        <vendorCode>1626010180</vendorCode>
        <country_of_origin>Китай</country_of_origin>
        <description>Триммер для волос VGR V-090 USB

Машинка для стрижки волос VGR-090 является незаменимым инструментом в работе мастеров моделирования стрижек. Она предназначена для профессионального использования в парикмахерских, салонах красоты, барбершопах и разрешена к применению в домашних условиях. Машинка для стрижки волос VGR-090 отличается прочным корпусом, устойчивым к воздействию вибрации, низким уровнем шума, стильным дизайном, плавным ходом острых лезвий, удобством и длительным сроком эксплуатации.

Характеристики:

- Бренд: VGR

- Номер модели: V-090

- Электропитание: 100-240 В 50/60 Гц

- Материал лезвия: Керамика 

- Насадки: 3

Комплектация:

- Машинка для волос

- 3 насадки

- Адаптер зарядки

- Чистящая щетка, масло

- Инструкция по эксплуатации
</description>
        <param name="Тип прибора">Универсальная машинка для стрижки</param>
        <param name="Тип питания">Аккумулятор</param>
        <param name="Количество насадок">3</param>
        <param name="Регулировка длины">Сменные насадки</param>
        <param name="Состояние">Новое</param>
        <param name="Триммер для окантовки ">Да</param>
      </offer>
      <offer id="1636501051" available="true">
        <url>https://aveon.net.ua/p1636501051-professionalnyj-fen-dlya.html</url>
        <oldprice>548</oldprice>
        <price>398</price>
        <currencyId>UAH</currencyId>
        <categoryId>30014688</categoryId>
        <picture>https://images.prom.ua/3845369181_professionalnyj-fen-dlya.jpg</picture>
        <picture>https://images.prom.ua/3845369338_professionalnyj-fen-dlya.jpg</picture>
        <picture>https://images.prom.ua/3845369351_professionalnyj-fen-dlya.jpg</picture>
        <picture>https://images.prom.ua/3845369337_professionalnyj-fen-dlya.jpg</picture>
        <pickup>false</pickup>
        <delivery>true</delivery>
        <name>Профессиональный фен для волос Mozer MZ-5920</name>
        <vendor>Mozer</vendor>
        <vendorCode>1636501051</vendorCode>
        <description>Профессиональный фен для волос Mozer MZ-5920

Moser MZ-5920 5000вт - профессиональный фен от известного бренда Moser. Мощный мотор производителен и долговечен. Скорость выдува оптимально подойдет для 

использования дома и в салоне, а так же подарит возможность для выполнения любых видов укладки и экспериментов. Корпус компактный. Есть защита мотора. Поток воздуха регулируемый - 2 скорости. Нагрев воздуха в 3 режимах. В комплекте насадка концентратор. Петля для подвешивания. Шнур длиной 1.5 м является достаточным и комфортным для работы.

Характеристики:


	Производитель: Mozer
	Модель: MZ-5920
	Вид: фен для волос
	Тип питания: Сеть 220 В
	Мощность: 5000W        
	Кол-во температурных режимов: 3      
	Количество скоростей: 2           
	Защита от перегрева: Есть
	Режим холодного воздуха: да
	Петля для подвешивания: да
	Длина шнура: 1,5 м


Комплектация


	Фен Mozer
	Насадка концентратор
	Коробка 

</description>
        <param name="Количество режимов работы">2</param>
        <param name="Количество скоростей">2</param>
        <param name="Количество температурных режимов">3</param>
        <param name="Холодный обдув">Да</param>
        <param name="Состояние">Новое</param>
        <param name="Защита от перегрева">Да</param>
        <param name="Петелька для подвешивания">Да</param>
        <param name="Длина сетевого шнура" unit="м">1.5</param>
        <param name="Тип">Фен</param>
      </offer>
      <offer id="1654269914" available="true">
        <url>https://aveon.net.ua/p1654269914-detskij-kovrik-dlya.html</url>
        <oldprice>623</oldprice>
        <price>473</price>
        <currencyId>UAH</currencyId>
        <categoryId>30017064</categoryId>
        <picture>https://images.prom.ua/3903431487_detskij-kovrik-dlya.jpg</picture>
        <picture>https://images.prom.ua/3903431744_detskij-kovrik-dlya.jpg</picture>
        <picture>https://images.prom.ua/3903431743_detskij-kovrik-dlya.jpg</picture>
        <picture>https://images.prom.ua/3903431745_detskij-kovrik-dlya.jpg</picture>
        <picture>https://images.prom.ua/3903431746_detskij-kovrik-dlya.jpg</picture>
        <picture>https://images.prom.ua/3903431742_detskij-kovrik-dlya.jpg</picture>
        <picture>https://images.prom.ua/3903431747_detskij-kovrik-dlya.jpg</picture>
        <picture>https://images.prom.ua/3903431751_detskij-kovrik-dlya.jpg</picture>
        <pickup>false</pickup>
        <delivery>true</delivery>
        <name>Детский коврик для рисования водой Aqua Magic Mat развивающий акваковрик с водными маркерами AVK</name>
        <vendor>Aqua Magic</vendor>
        <vendorCode>1654269914</vendorCode>
        <country_of_origin>Китай</country_of_origin>
        <description>Детский коврик для рисования водой Aqua Magic Mat развивающий акваковрик с водными маркерами

Все дети любят рисовать. Родители тоже любят, когда их дети рисуют, но только когда рисунки наблюдаются в предназначенных для этого местах, а не на обоях, дверях, одежде или в другом непотребном месте.

Как избежать большинства неприятностей, связанных с детским рисованием? Один из способов – купить коврик для рисования водой.

Ведь фломастер рисует водой и даже если родители не досмотрят и ребенок попытается порисовать им в другом месте, то водичка высохнет и не оставит следа – польза на лицо.

Освоить уникальную технику рисования водой поможет коврик для рисования.

Наберите в маркер обычную водичку и приступайте к творчеству!

Прикасаясь маркером к коврику, остаются цветные следы.

Спустя 4-7 минут рисунок высыхает и исчезает.

Набор поможет малышу развивать его творческий потенциал!

Размер коврика 90х60 см.

В комплекте также 2 ручки. 4 вида в ассортименте. Коврик не токсичный, без чернил. По мере высыхания воды, цвет рисунка становится бледнее. Игрушка удобна тем, что малыш не будет пачкать свои ручки и всё вокруг красками.

При контакте с жидкостью на коврике, волшебным образом, проявится созданный разноцветный рисунок. А после того, как поверхность просохнет, изображение исчезнет не оставляя за собой следов. Также рисуя специальным маркером с фонариком, ребенок будет наслаждаться ярким, светящимся рисунок. Изображение начинают затухать через 5 минут. Дожидаться пока рисунок исчезнет полностью нет необходимости - следующую картину можно рисовать поверх прежней!

 

Комплектация:


	
	Коврик;
	
	
	Водный фломастер;
	
	
	Маркер излучающий свет;
	
	
	2 листа мягких трафаретов;
	
	
	3 оттиска;
	
	
	Мягкий валик с нанесенной печатью;
	
	
	Резервуар для воды;
	
	
	Книжечка с примерами.
	

</description>
        <param name="Тип">Игровой коврик</param>
        <param name="Состояние">Новое</param>
      </offer>
      <offer id="1668280930" available="true">
        <url>https://aveon.net.ua/p1668280930-trimer-dlya-borody.html</url>
        <oldprice>989</oldprice>
        <price>839</price>
        <currencyId>UAH</currencyId>
        <categoryId>30014688</categoryId>
        <picture>https://images.prom.ua/3950652953_trimer-dlya-borody.jpg</picture>
        <picture>https://images.prom.ua/3950653049_trimer-dlya-borody.jpg</picture>
        <picture>https://images.prom.ua/3950653060_trimer-dlya-borody.jpg</picture>
        <picture>https://images.prom.ua/3950653053_trimer-dlya-borody.jpg</picture>
        <picture>https://images.prom.ua/3950653050_trimer-dlya-borody.jpg</picture>
        <pickup>false</pickup>
        <delivery>true</delivery>
        <name>Тример для бороды Rozia HQ 300, тример для окантовки, машинка для стрижки, тример для усов</name>
        <vendor>ROZIA</vendor>
        <vendorCode>1668280930</vendorCode>
        <country_of_origin>Китай</country_of_origin>
        <description>Тример для бороды и окантовки Rozia HQ 300.

Современные мода и стиль трактуют свои правила! Много мужчин носят бороду и усы и стремятся придавать им безупречную форму. Данное устройство призвано сделать уход за бородой и усами легким и удобным! Для того чтобы подравнять усы и бороду теперь хватит всего нескольких плавных движений, не требующих каких либо усилий!

Данная модель отличается от конкурентов стильным дизайном и совершенством исполнения. Металлический корпус придает вес, тример идеально лежит в руке и очень удобен в использовании. Емкий и качественный аккумулятор позволит не беспокоится о зарядке перед каждым использованием. Так же этот тример имеет необычный набор насадок - 1 мм; 2 мм; 3 мм; 4,5 мм; 6 мм. С таким набором насадок можно данный тример использовать для ухода не только за бородой, но и для стрижки головы.

Очень классный и качественный тример за относительно небольшие деньги! Это явный топ представитель линейки тримеров от Rozia.

Особенности:


	
	Триммер для стильных стрижек с идеальной окантовкой, стрижки бороды и усов;
	
	
	Корпус триммера металлический;
	
	
	Эффективная острая режущая головка, прочная и острая, для точной стрижки. Значительно повышает эффективность бритья;
	
	
	Кнопочный переключатель;
	
	
	Доступно для работы в течение 120 минут после полной зарядки.
	




Характеристики:


	
	Тип: триммер;
	
	
	Размер триммера 15 см;
	
	
	Мощность 5Вт;
	
	
	Машинка аккумуляторная;
	
	
	Время зарядки - 1.5 ч;
	
	
	Время работы после зарядки примерно 120 мин;
	
	
	Корпус: металлический;
	




Комплектация:

* Триммер

* Насадки 5 шт.

* USB шнур для зарядки

* Щетка

* Масло

* Расческа

* Заводская упаковка
</description>
        <param name="Вес" unit="кг">0.3</param>
        <param name="Тип элементов питания">Li-Ion</param>
        <param name="Индикатор заряда элементов питания">Да</param>
        <param name="Время заряда аккумулятора" unit="час">3</param>
        <param name="Время работы от аккумулятора" unit="мин">120</param>
        <param name="Керамическое покрытие">Нет</param>
        <param name="Насадка для стрижки бороды и усов">Да</param>
        <param name="Тип прибора">Машинка для стрижки бороды и усов</param>
        <param name="Количество насадок">5</param>
        <param name="Тип питания">Аккумулятор</param>
        <param name="Количество установок длины">6</param>
        <param name="Регулировка длины">Сменные насадки</param>
        <param name="Минимальная длина стрижки" unit="мм">0.1</param>
        <param name="Максимальная длина стрижки" unit="мм">6</param>
        <param name="Состояние">Новое</param>
        <param name="Триммер для окантовки ">Да</param>
      </offer>
      <offer id="1672176249" available="true">
        <url>https://aveon.net.ua/p1672176249-silikonovyj-detskij-nochnik.html</url>
        <oldprice>660</oldprice>
        <price>510</price>
        <currencyId>UAH</currencyId>
        <categoryId>30017053</categoryId>
        <picture>https://images.prom.ua/3963334937_silikonovyj-detskij-nochnik.jpg</picture>
        <picture>https://images.prom.ua/3963334938_silikonovyj-detskij-nochnik.jpg</picture>
        <picture>https://images.prom.ua/3963334939_silikonovyj-detskij-nochnik.jpg</picture>
        <picture>https://images.prom.ua/3963334940_silikonovyj-detskij-nochnik.jpg</picture>
        <picture>https://images.prom.ua/3963334941_silikonovyj-detskij-nochnik.jpg</picture>
        <picture>https://images.prom.ua/3963334942_silikonovyj-detskij-nochnik.jpg</picture>
        <picture>https://images.prom.ua/3963334943_silikonovyj-detskij-nochnik.jpg</picture>
        <picture>https://images.prom.ua/3963334944_silikonovyj-detskij-nochnik.jpg</picture>
        <picture>https://images.prom.ua/3963334945_silikonovyj-detskij-nochnik.jpg</picture>
        <pickup>false</pickup>
        <delivery>true</delivery>
        <name>Силиконовый детский ночник "Котик" 7 режимов</name>
        <vendorCode>1672176249</vendorCode>
        <description>Преимущества:

Ночник изготовлен из качественного материала
Имеет 7 режимов свечения
Приятный на ощупь
Оригинальный подарок для ребёнка. 


Описание:
Компактный LED светильник ночник в виде милого Котика, удобно использовать как настольный светильник и ночник для комнаты. Невероятно мягкий материал и красивый теплый свет свечения ночника можно оценить с первого включения и прикосновения к нему.
LED ночник – Лампа Котик имеет двойной режим света: теплый белый режим освещения и 7-цветной режим. Самое интересное в этом светильнике то, что она реагирует на прикосновение и тем самым меняет свой цвет. Купить ночник в спальню вы можете прямо сейчас у нас на сайте по скидке!

Характеристики:

Тип: лампа ночник
Цвет: белый
Количество режимов: 7
Питание: от батареек
Работает до 15 часов использование после полной зарядки

Комплектация:

1 шт.- светодиодный ночник- лампа Котик. 
1 шт. - инструкция (на английском языке)
Упаковка
</description>
        <param name="Состояние">Новое</param>
        <param name="Тип">Ночник</param>
        <param name="Цвет">Белый</param>
      </offer>
      <offer id="1684647623" available="true">
        <url>https://aveon.net.ua/p1684647623-trimmer-vgr-070.html</url>
        <oldprice>681</oldprice>
        <price>531</price>
        <currencyId>UAH</currencyId>
        <categoryId>30014688</categoryId>
        <picture>https://images.prom.ua/4003134471_trimmer-vgr-v-070.jpg</picture>
        <picture>https://images.prom.ua/4003134559_trimmer-vgr-v-070.jpg</picture>
        <picture>https://images.prom.ua/4003134560_trimmer-vgr-v-070.jpg</picture>
        <picture>https://images.prom.ua/4003134570_trimmer-vgr-v-070.jpg</picture>
        <picture>https://images.prom.ua/4003134583_trimmer-vgr-v-070.jpg</picture>
        <pickup>false</pickup>
        <delivery>true</delivery>
        <name>Триммер VGR V-070</name>
        <vendor>VGR</vendor>
        <vendorCode>1684647623</vendorCode>
        <country_of_origin>Китай</country_of_origin>
        <description>Описание

Машина создана для мужчин, которые ценят необычную точность стрижек.Выберите это для себя и позаботьтесь о своем идеальном внешнем виде!

Для профессионального использования в парикмахерских и дома.5 сменных насадок: 1, 2,3, 4 и 5 мм

Led дисплей: показывает уровень зарядки и турбо режим

Прочное острое лезвие из нержавеющей стали

Ширина ножа 40 мм

Тихий и долговечный двигатель

Плавная кнопка включения

Эргономичный корпус

Зарядка на 2 час, может работать непрерывно на 120 минут

Объем аккумулятора 600mAh

Легко чистить

Мощность: 3 Вт

В комплекте:

машинка для стрижки волос

5 гребешковых насадок,

масло для консервирования,

руководство пользователя

Технические характеристики:

Головка Лезвие из нержавеющей стали

Гладкий срез

5 насадок для регулировки длины 1мм, 2мм, 3мм, 4мм, 5мм

Ширина резки: 40 мм

Мощный роторный двигатель (высокая эффективность, длительный срок службы) мощностью 3 Вт

Эргономичный корпус

USB кабель

Комплектация


	машинка для стрижки волос
	5 гребешковых насадок
	масло для консервирования
	руководство пользователя

</description>
        <param name="Тип прибора">Универсальная машинка для стрижки</param>
        <param name="Количество насадок">5</param>
        <param name="Минимальная длина стрижки" unit="мм">1</param>
        <param name="Максимальная длина стрижки" unit="мм">5</param>
        <param name="Состояние">Новое</param>
        <param name="Тип питания">Аккумулятор</param>
      </offer>
      <offer id="1685734708" available="true">
        <url>https://aveon.net.ua/p1685734708-blender-crownberg-7331.html</url>
        <oldprice>1380</oldprice>
        <price>1230</price>
        <currencyId>UAH</currencyId>
        <categoryId>30018858</categoryId>
        <picture>https://images.prom.ua/4006561963_blender-crownberg-cb-7331.jpg</picture>
        <picture>https://images.prom.ua/4006561961_blender-crownberg-cb-7331.jpg</picture>
        <picture>https://images.prom.ua/4006561954_blender-crownberg-cb-7331.jpg</picture>
        <picture>https://images.prom.ua/4006561962_blender-crownberg-cb-7331.jpg</picture>
        <pickup>false</pickup>
        <delivery>true</delivery>
        <name>Блендер Crownberg Cb-7331 1000 Вт Стационарный</name>
        <vendor>CROWNBERG</vendor>
        <vendorCode>1685734708</vendorCode>
        <description>Универсальный стационарный блендер с насадкой кофемолка, позволяет смешивать и перемалывать любые продукты, в том числе и кофейные зерна. Острые ножи выполнены из высококачественной нержавеющей стали. Чаша с ручкой и мерной шкалой сделана из стекла и имеет объём 1800 мл. Имеет 2 скоростных режима. Импульсный режим работы. Мощность 1000 Вт. Легко моется и чистится. 

Преимущества:


	Импульсный режим работы;
	Защитный блокировочный механизм;
	Мотор с защитой от перегрева;
	Ножи из нержавеющей стали;
	Насадка для измельчения.


Характеристики :

 


	Мощность: 1000 Вт;
	Номинальное напряжение: 220-230 В;
	Номинальная частота: 50 Гц;
	Емкость кувшина: 1.8 л;
	2 скоростных режима работы.

</description>
        <param name="Потребляемая мощность" unit="Вт">1000</param>
        <param name="Тип управления">Механическое</param>
        <param name="Количество скоростей">2</param>
        <param name="Тип блендера">Стационарный</param>
        <param name="Состояние">Новое</param>
      </offer>
      <offer id="1685859169" available="true">
        <url>https://aveon.net.ua/p1685859169-elektro-utka-trek.html</url>
        <oldprice>405</oldprice>
        <price>255</price>
        <currencyId>UAH</currencyId>
        <categoryId>30017064</categoryId>
        <picture>https://images.prom.ua/4006883571_elektro-utka-trek.jpg</picture>
        <picture>https://images.prom.ua/4006883775_elektro-utka-trek.jpg</picture>
        <picture>https://images.prom.ua/4006883774_elektro-utka-trek.jpg</picture>
        <picture>https://images.prom.ua/4006883776_elektro-utka-trek.jpg</picture>
        <picture>https://images.prom.ua/4006883778_elektro-utka-trek.jpg</picture>
        <pickup>false</pickup>
        <delivery>true</delivery>
        <name>Электро утка, трек, горка, игрушки для мальчиков и девочек, утки, игрушка для подъема по лестнице</name>
        <vendorCode>1685859169</vendorCode>
        <country_of_origin>Китай</country_of_origin>
        <description>Характеристики:


	Название: электрическая игрушка для альпинизма и лестницы
	Материал: АБС-пластик


Характеристики:


	светильник и музыка
	Размеры: 25,5*14 см/10,04*5,51 дюймов
	Вес: около 300 г


Комплект:


	маленькие желтые уточки
	3 предмета в комплекте из горки трек
	Трек база
	Арки доски карточки 


 
</description>
        <param name="Материал">Пластик</param>
        <param name="Пол">Унисекс</param>
        <param name="Цвет">Желтый</param>
        <param name="Состояние">Новое</param>
      </offer>
      <offer id="1691328068" available="true">
        <url>https://aveon.net.ua/p1691328068-pover-bank-smart.html</url>
        <oldprice>518</oldprice>
        <price>368</price>
        <currencyId>UAH</currencyId>
        <categoryId>70180949</categoryId>
        <picture>https://images.prom.ua/4025329636_pover-bank-smart.jpg</picture>
        <picture>https://images.prom.ua/4025329724_pover-bank-smart.jpg</picture>
        <picture>https://images.prom.ua/4025329731_pover-bank-smart.jpg</picture>
        <pickup>false</pickup>
        <delivery>true</delivery>
        <name>Повер банк Smart Tech 50000 mAh. Power Bank</name>
        <vendorCode>1691328068</vendorCode>
        <country_of_origin>Китай</country_of_origin>
        <description>Технические характеристики •

Тип: Внешний аккумулятор для заряда портативных устройств

Заряжаемые устройства: смартфоны, телефоны, iPod, iPhone, планшеты и другие

Подключение: USB

Емкость, mAh: 50000 

Технология: Li-Ion

Зарядка: от USB

Выход1: DC 5.0В, 1 А (Макс)

Выход2: DC 5.0В, 2 А (Макс)

Выход3: DC 5.0В, 2.1 А (Макс)

Вход: DC 5В, 1 А (Макс)



• Подробная информация •

Power Bank Smart Tech 50000 - внешний аккумулятор, надежный источник питания, который станет хорошим другом для путешественников, деловых и активных людей. Говорите по телефону, слушайте музыку, играйте, фотографируйте и снимайте больше с помощью Power Bank Smart Tech 50000 . 

Виробник Китай. Даний продукт є копією. Портативный аккумулятор Smart Tech 50000mAh это уникальное устройство, которое позволит вашему телефону или планшету работать дольше. Power Bank очень компактен, не займет много места в рюкзаке или сумке, а его наличие позволит подзарядить смартфон в любом удобном месте. Также Power Bank Smart Tech 50000mAh отличает лаконичный и стильный дизайн. Корпус выполнен из прочного пластика. На торце размещен разъем для зарядки самого аккумулятора и LED фонарик, а сбоку на корпусе размещены три USB разъема для зарядки от него других устройств. Также на корпусе имеются индикатор степени зарядки внешнего аккумулятора и кнопка включения. 

• Комплектация •

Power Bank

Micro USB кабель

Заводская упаковка
</description>
        <param name="Тип аккумулятора">Li-Ion</param>
        <param name="Емкость аккумулятора" unit="мА/ч">50000</param>
        <param name="Цвет корпуса">Коричневый</param>
        <param name="Состояние">Новое</param>
      </offer>
      <offer id="1707263952" available="true">
        <url>https://aveon.net.ua/p1707263952-blender-pogruzhnoj-chashej.html</url>
        <oldprice>1425</oldprice>
        <price>1275</price>
        <currencyId>UAH</currencyId>
        <categoryId>30018858</categoryId>
        <picture>https://images.prom.ua/4073283388_blender-pogruzhnoj-s.jpg</picture>
        <picture>https://images.prom.ua/4073283383_blender-pogruzhnoj-s.jpg</picture>
        <picture>https://images.prom.ua/4073283385_blender-pogruzhnoj-s.jpg</picture>
        <picture>https://images.prom.ua/4073283384_blender-pogruzhnoj-s.jpg</picture>
        <picture>https://images.prom.ua/4073283561_blender-pogruzhnoj-s.jpg</picture>
        <pickup>false</pickup>
        <delivery>true</delivery>
        <name>Блендер погружной с чашей 3в1 TEXET 03THB миниизмельчитель и венчик для взбивания, 3 насадки, 450 Вт</name>
        <vendor>TeXet</vendor>
        <vendorCode>1707263952</vendorCode>
        <description>Очень сложно представить современную кухню без блендера. Этот помощник гарантирует ускоренный и комфортный процесс приготовления пищи. Он используется для смешивания соусов, детского питания, майонеза, измельчения лука, мяса, фруктов и овощей, смешивания коктейлей, рубки льда.

В комплект представленной модели входит насадка венчик, насадка блендер и насадка измельчитель, моторная часть. Венчик, режущая часть измельчителя и погружная часть блендера изготовлены из высококачественной нержавеющей стали, переходники изготовлены из пластика.

Блендер погружной измельчитель TEXET  мгновенно смешивает и измельчает ваши полезные ингредиенты как можно быстрее, превращая их в полезные и вкусные блюда, приготовленные в вашем доме.

Достоинства:


	Имеет сменные лезвия, которые используются для взбивания сливок, яиц, соусов и т.д.
	Ножка из нержавеющей стали с защитой от разбрызгивания.
	Оборудован мощным двигателем 450 Вт, поддерживающим работу с твердыми ингредиентами.
	Уникальная форма корпуса без борозд на поверхности обеспечивает лёгкость очистки.


Характеристики:


	Материал корпуса: пластик
	Материал погружной части: нержавеющая сталь.
	Мощность: 450 Вт
	Количество насадок: 3
	Питание: 220-240V 50/60Hz


Комплектация:


	Блендер TEXET;
	Насадка 3шт.;
	Стакан 1шт;
	Инструкция;
	Заводская упаковка.

</description>
        <param name="Потребляемая мощность" unit="Вт">800</param>
        <param name="Тип управления">Механическое</param>
        <param name="Состояние">Новое</param>
      </offer>
      <offer id="1716502586" available="true">
        <url>https://aveon.net.ua/p1716502586-mashinka-dlya-strizhki.html</url>
        <oldprice>1065</oldprice>
        <price>915</price>
        <currencyId>UAH</currencyId>
        <categoryId>30014688</categoryId>
        <picture>https://images.prom.ua/4102729546_mashinka-dlya-strizhki.jpg</picture>
        <picture>https://images.prom.ua/4102729519_mashinka-dlya-strizhki.jpg</picture>
        <picture>https://images.prom.ua/4102729521_mashinka-dlya-strizhki.jpg</picture>
        <picture>https://images.prom.ua/4102729533_mashinka-dlya-strizhki.jpg</picture>
        <picture>https://images.prom.ua/4102729539_mashinka-dlya-strizhki.jpg</picture>
        <picture>https://images.prom.ua/4102729544_mashinka-dlya-strizhki.jpg</picture>
        <pickup>false</pickup>
        <delivery>true</delivery>
        <name>Машинка для стрижки волос 5в1 VGR V-102 триммер для бороды и усов</name>
        <vendor>VGR</vendor>
        <vendorCode>1716502586</vendorCode>
        <description>Машинка для стрижки волос 5в1 VGR V-102 триммер для бороды и усов

Машинка для стрижки волос VGR V-102 триммер для бороды и усов – выполнена в стильном камуфляжном дизайне из высококачественных материалов. Машинка для стрижки волос очень проста в использовании, в комплекте есть все необходимые насадки для идеальной стрижки.

Профессиональная машинка для стрижки волос VGR V-102 отличается легкостью и компактностью, практически не чувствуется в руке. Работает от аккумулятора, что позволяет комфортно перемещаться при работе, не сковывая и не ограничивая движения. Заряжается очень быстро и зарядки хватает примерно на два часа работы, что очень удобно для работы мастера-парикмахера, когда нужно принять много людей.



Быстросъемный ножевой блок, изготовленный из нержавеющей стали, гарантирует длительный срок службы изделия. Вы с легкостью сможете очистить или заменить нож при необходимости. Высококачественная сталь позволяет выполнять точные работы максимально близко к коже.

В комплектации щеточка для чистки и специальное масло для ножей. Рекомендуется периодически смазывать лезвия для качественной работы машины. После нанесения масла необходимо, чтобы машинка поработала несколько секунд для равномерного распределения смазки на поверхности.

Характеристики:


	Длительная работа
	Ножи из нержавеющей стали
	Индикатор зарядки аккумулятора
	Аккумулятор: литиевая батарея 600 mAh
	Дисплей
	Быстрая зарядка
	Время зарядки: 2 часа
	Время работы: 150 минут
	Ширина лезвия: 40 мм
	Работа: без шнура
	Малый вес и габариты
	Легко ложится даже в небольшую ладонь
	Долговечный и высокопроизводительный
	Минимальная высота среза 0.1 мм
	Работает от сети 100 – 240 В
	Мощность 3Вт
	Размер: 15,7*4,6*4,4 см


Комплектация:


	Машинка для стрижки волос VGR V-102;
	гребневые насадки-5 шт (3мм, 6мм, 9мм, 12мм);
	Узкий триммер 1 шт;
	Триммер для носа 1 шт;
	Дизайнерский триммер 1 шт;
	Насадка для стрижки волос 1шт;
	Голызна головка 1 шт;
	Масло
	USB кабель
	Щеточка для чистки
	Коробка.

</description>
        <param name="Щеточка для чистки">Да</param>
        <param name="Тип питания">Аккумулятор</param>
        <param name="Количество установок длины">5</param>
        <param name="Состояние">Новое</param>
      </offer>
      <offer id="1717637592" available="true">
        <url>https://aveon.net.ua/p1717637592-professionalnaya-mashinka-dlya.html</url>
        <oldprice>608</oldprice>
        <price>458</price>
        <currencyId>UAH</currencyId>
        <categoryId>30014688</categoryId>
        <picture>https://images.prom.ua/4106393583_professionalnaya-mashinka-dlya.jpg</picture>
        <picture>https://images.prom.ua/4106393576_professionalnaya-mashinka-dlya.jpg</picture>
        <picture>https://images.prom.ua/4106393577_professionalnaya-mashinka-dlya.jpg</picture>
        <picture>https://images.prom.ua/4106393579_professionalnaya-mashinka-dlya.jpg</picture>
        <picture>https://images.prom.ua/4106393580_professionalnaya-mashinka-dlya.jpg</picture>
        <picture>https://images.prom.ua/4106393582_professionalnaya-mashinka-dlya.jpg</picture>
        <picture>https://images.prom.ua/4106393584_professionalnaya-mashinka-dlya.jpg</picture>
        <picture>https://images.prom.ua/4106393585_professionalnaya-mashinka-dlya.jpg</picture>
        <picture>https://images.prom.ua/4106393581_professionalnaya-mashinka-dlya.jpg</picture>
        <picture>https://images.prom.ua/4106393578_professionalnaya-mashinka-dlya.jpg</picture>
        <pickup>false</pickup>
        <delivery>true</delivery>
        <name>Профессиональная машинка для стрижки волос 8 насадок VGR V-120 Pro Черный + Ножницы</name>
        <vendor>VGR</vendor>
        <vendorCode>1717637592</vendorCode>
        <country_of_origin>Китай</country_of_origin>
        <description>Описание Профессиональная машинка для стрижки волос 8 насадок VGR V-120 Pro Черный + Ножницы

Профессиональная машинка для стрижки волос 8 насадок VGR V-120 Pro Черный + Ножницы

Машинка триммер VGR V 120 сочетает в себе машинку для стрижки волос и бороды со сменными насадками (от 3 до 20 мм). Используя сам триммер без насадки, вы сможете создать ровные контуры стрижки, подбрить баки или начисто выбрить шею.

Кроме того, его можно использовать для удаления нежелательных волос на теле. Эргономичный, легкий и компактный дизайн позволяет с легкостью владеть инструментом даже новичку.

Главным преимуществом данной модели есть наличие насадок - 3, 6, 9, 12, 16, 20 мм, а также насадки с правым и левым уклоном для удобного моделирования бороды.

В комплекте есть расческа, щеточка для очистки и масло для лезвий.

ОСОБЕННОСТИ:


	Со сменными насадками возможно придать идеальную форму бороде и усам;
	Оборудована лезвиями из нержавеющей стали, гарантирующими аккуратный ровный срез она аккуратно срезает волоски, не оставляя каких-либо следов на чувствительной коже;
	Она функциональна и проста в управлении;
	Машинка работает от сети;
	Петелька для подвешивания плойки;
	Имеет стильный дизайн;
	Удобно ложится в руке и имеет лёгкий вес;
	Идеальный помощник в командировках.


ХАРАКТЕРИСТИКИ:





	Модель: VGR V 120;
	Тип: Машинка для стрижки;
	Тип питания: от сети 220 Вт;
	Габариты (ДхШхГ): 18,5 x 6,8 x 5,2 см;
	Режущие лезвия из керамики высокой точностью;
	Тип чистки: сухая;
	Регулировка длины: сменные насадки;
	Количество сменных насадок: 8 (3, 6, 9, 12, 16, 20 мм, с правым уклоном, с левым уклоном)
	Установка длины стрижки: от 3 до 20 мм;
	Петелька для подвешивания плойки;
	Вес: 0,43 кг;
	Длина шнура: 1.8 м.:
	Цвет: черный.


КОМПЛЕКТАЦИЯ:








	Машинка для стрижки волос VGR V-120
	8 насадок
	Ножницы
	Расческа
	Щетка для чистки
	Масло
	Инструкция
	Заводская упаковка.

</description>
        <param name="Тип прибора">Универсальная машинка для стрижки</param>
        <param name="Количество насадок">7</param>
        <param name="Тип питания">Аккумулятор</param>
        <param name="Количество установок длины">7</param>
        <param name="Регулировка длины">Сменные насадки</param>
        <param name="Состояние">Новое</param>
      </offer>
      <offer id="1717651271" available="true">
        <url>https://aveon.net.ua/p1717651271-mashinka-vgr-007.html</url>
        <oldprice>608</oldprice>
        <price>458</price>
        <currencyId>UAH</currencyId>
        <categoryId>30014688</categoryId>
        <picture>https://images.prom.ua/4106453696_mashinka-vgr-007-dlya.jpg</picture>
        <picture>https://images.prom.ua/4106453694_mashinka-vgr-007-dlya.jpg</picture>
        <picture>https://images.prom.ua/4106453693_mashinka-vgr-007-dlya.jpg</picture>
        <picture>https://images.prom.ua/4106453695_mashinka-vgr-007-dlya.jpg</picture>
        <picture>https://images.prom.ua/4106453692_mashinka-vgr-007-dlya.jpg</picture>
        <pickup>false</pickup>
        <delivery>true</delivery>
        <name>Машинка VGR-007 для стрижки волос и бороды аккумуляторная беспроводная профессиональная с 3 насадками 5W</name>
        <vendor>VGR</vendor>
        <vendorCode>1717651271</vendorCode>
        <country_of_origin>Китай</country_of_origin>
        <description>Описание Машинка для стрижки волос и бороды аккумуляторная беспроводная профессиональная с 3 насадками VGR 5W Черная (V-007)

Машинка для стрижки волос и бороды аккумуляторная беспроводная профессиональная с 3 насадками VGR 5W Черная (V-007) - Подравнивайте, брейте, детализируйте и очерчивайте волосы с помощью беспроводной машинки VGR.

Поставляется с тремя сменными насадками для стрижки на 1 мм, 2 мм, 3 мм.

Характеристики:


	Мощность: 5 Вт
	Ширина ножа: 40 мм
	Время работы от аккумулятора: 120 минут
	Время полной зарядки: 1.5 часа
	Емкость аккумулятора: 500 мАч
	Размеры: 15 х 3.7 х 3 см


Комплектация:


	Машинка для стрижки VGR
	Насадки - 3 шт.
	Масло для ножей
	Щеточка для очистки
	Кабель USB для зарядки
	Инструкция
	Заводская упаковка

</description>
        <param name="Тип прибора">Универсальная машинка для стрижки</param>
        <param name="Количество насадок">3</param>
        <param name="Тип питания">Аккумулятор</param>
        <param name="Количество установок длины">3</param>
        <param name="Регулировка длины">Сменные насадки</param>
        <param name="Состояние">Новое</param>
      </offer>
      <offer id="1728874696" available="true">
        <url>https://aveon.net.ua/p1728874696-poverbank-led-lighting.html</url>
        <oldprice>1125</oldprice>
        <price>975</price>
        <currencyId>UAH</currencyId>
        <categoryId>70180949</categoryId>
        <picture>https://images.prom.ua/4142316633_poverbank-led-lighting.jpg</picture>
        <picture>https://images.prom.ua/4142317088_poverbank-led-lighting.jpg</picture>
        <picture>https://images.prom.ua/4142317090_poverbank-led-lighting.jpg</picture>
        <picture>https://images.prom.ua/4142317089_poverbank-led-lighting.jpg</picture>
        <picture>https://images.prom.ua/4142317093_poverbank-led-lighting.jpg</picture>
        <picture>https://images.prom.ua/4142317092_poverbank-led-lighting.jpg</picture>
        <picture>https://images.prom.ua/4142317094_poverbank-led-lighting.jpg</picture>
        <picture>https://images.prom.ua/4142317096_poverbank-led-lighting.jpg</picture>
        <picture>https://images.prom.ua/4142317097_poverbank-led-lighting.jpg</picture>
        <pickup>false</pickup>
        <delivery>true</delivery>
        <name>Повербанк LED Lighting Power Bank X9 20000 mAh Внешний аккумулятор Портативная зарядка</name>
        <vendorCode>1728874696</vendorCode>
        <country_of_origin>Китай</country_of_origin>
        <description>Повербанк LED Lighting Power Bank X9 20000 mAh



Повербанк LED Lighting Power Bank X9 20000 mAh

Power Bank X9 20000 mAh – стильный аксессуар, способный продлить время автономной работы вашего смартфона или планшета. Power Bank станет отличным помощником для тех, кто любит путешествовать, отдыхать на природе или использует свои мобильные девайсы по полной.

 



 

 

 

Особенности:


	Высокое качество сборки и материалов
	Цифровая индикация заряда
	Сравнительно компактные размеры
	Удобство переноски и простота использования
	Несколько уровней защиты для безопасной зарядки
	Фонарик
	3 USB






 

 

 

Характеристики:


	Емкость, мА·час: 20000
	Технология: Li-Ion
	Зарядка: от USB
	Разъемы: 3х USB, micro USB
	Вход: 5В, 2.0 А (Макс)
	Выход: 5.0В, 2.1А (Макс)
	Материал: ABS пластик

</description>
        <param name="Тип аккумулятора">Li-Ion</param>
        <param name="Емкость аккумулятора" unit="мА/ч">20000</param>
        <param name="Материал корпуса">Пластик</param>
        <param name="Тип">Универсальная батарея</param>
        <param name="Выходное напряжение" unit="В">5</param>
        <param name="Состояние">Новое</param>
        <param name="Особенности">Фонарик|Индикатор уровня заряда</param>
      </offer>
      <offer id="1733284760" available="true">
        <url>https://aveon.net.ua/p1733284760-fonar-lampa-solnechnoj.html</url>
        <oldprice>443</oldprice>
        <price>293</price>
        <currencyId>UAH</currencyId>
        <categoryId>70181491</categoryId>
        <picture>https://images.prom.ua/4155058284_fonar-lampa-s-solnechnoj.jpg</picture>
        <picture>https://images.prom.ua/4155058277_fonar-lampa-s-solnechnoj.jpg</picture>
        <picture>https://images.prom.ua/4155058283_fonar-lampa-s-solnechnoj.jpg</picture>
        <picture>https://images.prom.ua/4155058310_fonar-lampa-s-solnechnoj.jpg</picture>
        <pickup>false</pickup>
        <delivery>true</delivery>
        <name>Фонарь-лампа с солнечной панелью EP-020</name>
        <vendorCode>1733284760</vendorCode>
        <country_of_origin>Китай</country_of_origin>
        <description>Характеристики и описание

Фонарь-лампа с солнечной панелью EP-020

Информация о товаре:


	Размер: 82*82*137 мм
	Емкость аккумулятора: оливково-кислотный аккумулятор емкостью 900 мАч.
	Солнечная панель: 6 В 1 Вт
	Материал корпуса: пластик
	Режим переключения: ручной
	Время освещения: 15 час
	Количество светодиодов: 20 шт., высокое качество 5730SMD
	1 шт. 6 В 1 Вт солнечная панель с кабелем 3 м
	USB-зарядка
	Крючок для удобства подвешивания
	Зарядное отверстие
	Зарядка солнечной панели


 



 

 



 

 

 



 

 

 
</description>
        <param name="Тип питания">Аккумулятор</param>
        <param name="Состояние">Новое</param>
        <param name="Тип заряда">Солнечные батареи</param>
        <param name="Цвет">Оливковый</param>
      </offer>
      <offer id="1739856872" available="true">
        <url>https://aveon.net.ua/p1739856872-solnechnaya-zaryadnaya-stantsiya.html</url>
        <oldprice>1455</oldprice>
        <price>1305</price>
        <currencyId>UAH</currencyId>
        <categoryId>70181491</categoryId>
        <picture>https://images.prom.ua/4175379949_solnechnaya-zaryadnaya-stantsiya.jpg</picture>
        <picture>https://images.prom.ua/4175379950_solnechnaya-zaryadnaya-stantsiya.jpg</picture>
        <pickup>false</pickup>
        <delivery>true</delivery>
        <name>Солнечная зарядная станция + LED фонарь Junai JA-2007 с лампочками + Power Bank</name>
        <vendor>JunAi</vendor>
        <vendorCode>1739856872</vendorCode>
        <country_of_origin>Китай</country_of_origin>
        <description>Солнечная зарядная станция + LED фонарь Junai JA-2007 с лампочками + Power Bank

Представляем многофункциональную систему JunAi JA-2007 набор включает в себя солнечную панель, аккумулятор 5000 мАч, фонарик, динамик с Bluetooth и FM радио, 2 светодиодные лампы, кабель для зарядки различных гаджетов и наплечный ремень. Система допускает несколько вариантов освещения, встроенный фонарик спереди и лампу сбоку.

Также в комплект входят 2 светодиодные лампы с кабелями. Лампы имеют отдельные переключатели, что позволяет настраивать их в соответствии с потребностями. При одновременном использовании ламп заряда батареи хватает на 10 часов.  В системе предусмотрена возможность зарядки разных типов мобильных устройств – телефонов GSM, планшетов, ноутбуков, i-Pod, MP3, GPS и др. 

Батарею можно заряжать двумя способами – от сети 220 В или от солнечной батареи. Предусмотрен индикатор уровня заряда аккумулятора, а также светодиодная аварийная лампа. Устройство широко применяется на охоте и рыбалке, в походах, кемпингах, для оборудования дач, караванов и палаток, т.е. в качестве дополнительного возобновляемого источника энергии в разных ситуациях.



Характеристики:


	Аккумуляторная осветительная станция с солнечной панелью и дополнительными выносными лампочками
	Материал фонарика: пластик.
	Источник света: Cree XHP 30 + COB панель + 2шт. выносные лампы.
	Количество режимов работы: 3 режима (100% P30, 1000% COB, 50% COB) + функция PowerBank+ можно подключить к четырем выносным лампам (2шт. в комплекте).
	Размеры: общие размеры с учетом ручки 168х145х67 мм.
	Питание: Работает от встроенного литий-ионного аккумулятора. Зарядка происходит через USB-кабель или солнечную панель. Есть функция PowerBank. .


Комплектация: 


	Станция,
	кабель-разветвитель, 2шт.
	выносная лампа,
	выносная солнечная панель.


Если устройство не используется в течение длительного времени, заряжайте аккумулятор каждые 3 месяца в течение 13 часов. В противном случае срок службы батареи сократится.

Рекомендации:

Для увеличения производительности устройства рекомендуем:


	Бережно храните солнечную панель, старайтесь не повредить покрытие. 
	Протирайте солнечную панель, чтобы удалить пыль.
	Направляйте солнечную панель прямо на солнце. 
	Полностью зарядите устройство перед первым использованием от сети 220 вольт (от солнца первая зарядка рекомендуется один день под ярким солнцем 24 часа)



</description>
        <param name="Тип питания">Аккумулятор</param>
        <param name="Состояние">Новое</param>
        <param name="Особенности фонаря">Зарядка для телефона</param>
      </offer>
      <offer id="1741646999" available="true">
        <url>https://aveon.net.ua/p1741646999-poverbank-solnechnoj-panelyu.html</url>
        <oldprice>675</oldprice>
        <price>525</price>
        <currencyId>UAH</currencyId>
        <categoryId>70180949</categoryId>
        <picture>https://images.prom.ua/4181714417_poverbank-s-solnechnoj.jpg</picture>
        <picture>https://images.prom.ua/4181714386_poverbank-s-solnechnoj.jpg</picture>
        <picture>https://images.prom.ua/4181699196_poverbank-s-solnechnoj.jpg</picture>
        <picture>https://images.prom.ua/4181699198_poverbank-s-solnechnoj.jpg</picture>
        <pickup>false</pickup>
        <delivery>true</delivery>
        <name>Повербанк с солнечной панелью (power bank) 50000mAh (2400mAh) Boro JS-5</name>
        <vendor>Boro</vendor>
        <vendorCode>1741646999</vendorCode>
        <country_of_origin>Китай</country_of_origin>
        <description>Портативный аккумулятор (power bank) 50000mAh (2400mAh) Boro JS-5 

Внешний аккумулятор отличается стильным дизайном, высокой емкостью батареи и подключением нескольких устройств.

Батарея высокой емкости имеет относительно небольшие габариты и стильный дизайн, широкую область применения, долговечность, высокую экономичность.

Имеются 4 индикатора (100, 75, 50, 25%), что показывает уровень заряда батареи. Подойдет для зарядки любых портативных устройств.

Имеет защиту от чрезмерной зарядки, защиту от короткого замыкания, защиту от чрезмерной разрядки.

Power bank можно использовать в повседневной жизни, на отпуске и не только. Благодаря большой емкости и 2 интерфейсным портам он может заряжать несколько устройств одновременно.

В комплекте идет кабель для подзарядки. Поддерживает быструю зарядку.

С одной стороны корпуса есть солнечная панель как альтернативная форма зарядки, с маленьким компасом, а с другой – LED фонарь. В торце есть пластиковая петля.


	Тип : Универсальная батарея
	Тип аккумулятора : Li-Ion
	Входное напряжение: 5 В/2А
	Выходное напряжение: 5 В/2А
	Емкость аккумулятора: 50000mAh (2400mAh)
	Зарядка батареи : От USB, солнечная панель
	Материал корпуса: Пластик
	Набор переходников: Нет
	Особенности : компас, Индикатор уровня заряда
	Разъемы : micro USB, USBx2

</description>
        <param name="Тип аккумулятора">Li-Ion</param>
        <param name="Емкость аккумулятора" unit="мА/ч">50000</param>
        <param name="Тип">Универсальная батарея</param>
        <param name="Состояние">Новое</param>
        <param name="Зарядка батареи">От USB|От солнечной энергия</param>
      </offer>
      <offer id="1742337664" available="true">
        <url>https://aveon.net.ua/p1742337664-lampa-nastolnaya-gibkoj.html</url>
        <oldprice>495</oldprice>
        <price>345</price>
        <currencyId>UAH</currencyId>
        <categoryId>30017064</categoryId>
        <picture>https://images.prom.ua/4183271917_lampa-nastolnaya-na.jpg</picture>
        <picture>https://images.prom.ua/4183271915_lampa-nastolnaya-na.jpg</picture>
        <picture>https://images.prom.ua/4183271914_lampa-nastolnaya-na.jpg</picture>
        <picture>https://images.prom.ua/4183271916_lampa-nastolnaya-na.jpg</picture>
        <pickup>false</pickup>
        <delivery>true</delivery>
        <name>Лампа настольная на гибкой ножке с органайзером и подставкой телефона Quite Light Pig с точилкой розовый</name>
        <vendorCode>1742337664</vendorCode>
        <country_of_origin>Китай</country_of_origin>
        <description>Описание Лампа настольная на гибкой ножке с органайзером для ручек и подставкой телефона Quite Light Pig с точилкой карандашей, питание от USB Розовая

Лампа настольная на гибкой ножке с органайзером для ручек и подставкой телефона Quite Light Pig с точилкой карандашей, питание от USB Розовая

Настольная гибкая лама многофункциональная, изготовленная из матового ABS пластика. Оснащена настольная лампа встроенной точилкой для карандашей, которая имеет подсветку в режиме ночника. Питание лампы происходит через кабель micro USB-USB. Так же вы можете установить на подставку свой смартфон для просмотра видео либо канцелярские принадлежности.

На корпусе имеются органайзер для ручек и других небольших предметов, отсек-подставка для телефона. Так же, милый дизайн, который впишется в любой интерьер. В комплект входит micro-USB и USB шнур.

Характеристики:


	Материал: ABS пластик;
	Тип лампы: Светодиодная
	Управление: переключатель на задней стороне корпуса
	Кнопка включения на корпусе: Есть;
	Питание: USB
	Зарядка: вход micro USB
	Вес : 160 грамм.


Комплектация:


	Лампа LED;
	Кабель питания USB-micro USB;
	Фирменная коробка.

</description>
        <param name="Тип">Настольная лампа</param>
        <param name="Цвет">Розовый</param>
        <param name="Состояние">Новое</param>
        <param name="Тип крепления">На поверхность</param>
        <param name="Тип лампы">Светодиодная</param>
      </offer>
      <offer id="1742342542" available="true">
        <url>https://aveon.net.ua/p1742342542-lampa-nastolnaya-organajzerom.html</url>
        <oldprice>495</oldprice>
        <price>345</price>
        <currencyId>UAH</currencyId>
        <categoryId>30017064</categoryId>
        <picture>https://images.prom.ua/4183286186_lampa-nastolnaya-s.jpg</picture>
        <picture>https://images.prom.ua/4183286185_lampa-nastolnaya-s.jpg</picture>
        <picture>https://images.prom.ua/4183286187_lampa-nastolnaya-s.jpg</picture>
        <picture>https://images.prom.ua/4183286189_lampa-nastolnaya-s.jpg</picture>
        <picture>https://images.prom.ua/4183286188_lampa-nastolnaya-s.jpg</picture>
        <pickup>false</pickup>
        <delivery>true</delivery>
        <name>Лампа настольная с органайзером для ручек и подставкой телефона Quite Light Snail с точилкой Синий</name>
        <vendorCode>1742342542</vendorCode>
        <country_of_origin>Китай</country_of_origin>
        <description>Описание Лампа настольная на гибкой ножке с органайзером для ручек и подставкой телефона Quite Light Snail с точилкой карандашей, питание от USB Синяя

Лампа настольная на гибкой ножке с органайзером для ручек и подставкой телефона Quite Light Snail с точилкой карандашей, питание от USB Синяя

Настольная гибкая лама многофункциональная, изготовленная из матового ABS пластика. Оснащена настольная лампа встроенной точилкой для карандашей, которая имеет подсветку в режиме ночника. Питание лампы происходит через кабель micro USB-USB. Так же вы можете установить на подставку свой смартфон для просмотра видео либо канцелярские принадлежности.

На корпусе имеются органайзер для ручек и других небольших предметов, отсек-подставка для телефона. Так же, милый дизайн, который впишется в любой интерьер. В комплект входит micro-USB и USB шнур.

Характеристики:


	Материал: ABS пластик;
	Тип лампы: Светодиодная
	Управление: переключатель на задней стороне корпуса
	Кнопка включения на корпусе: Есть;
	Питание: USB
	Зарядка: вход micro USB
	Вес : 160 грамм.


Комплектация:


	Лампа LED;
	Кабель питания USB-micro USB;
	Фирменная коробка.

</description>
        <param name="Материал каркаса">пластик</param>
        <param name="Тип">Настольная лампа</param>
        <param name="Цвет">Синий</param>
        <param name="Состояние">Новое</param>
        <param name="Тип крепления">На поверхность</param>
        <param name="Тип лампы">Светодиодная</param>
      </offer>
      <offer id="1742344802" available="true">
        <url>https://aveon.net.ua/p1742344802-lampa-nastolnaya-tochilkoj.html</url>
        <oldprice>495</oldprice>
        <price>345</price>
        <currencyId>UAH</currencyId>
        <categoryId>30017064</categoryId>
        <picture>https://images.prom.ua/4183298238_lampa-nastolnaya-s.jpg</picture>
        <picture>https://images.prom.ua/4183298239_lampa-nastolnaya-s.jpg</picture>
        <picture>https://images.prom.ua/4183298235_lampa-nastolnaya-s.jpg</picture>
        <picture>https://images.prom.ua/4183298236_lampa-nastolnaya-s.jpg</picture>
        <picture>https://images.prom.ua/4183298234_lampa-nastolnaya-s.jpg</picture>
        <pickup>false</pickup>
        <delivery>true</delivery>
        <name>Лампа настольная с точилкой  органайзером для ручек и подставкой телефона Зеленый</name>
        <vendorCode>1742344802</vendorCode>
        <country_of_origin>Китай</country_of_origin>
        <description>Описание Лампа настольная на гибкой ножке с органайзером для ручек и подставкой телефона Quite Light Rabbit с точилкой карандашей, питание от USB Зеленая

Лампа настольная на гибкой ножке с органайзером для ручек и подставкой телефона Quite Light Rabbit с точилкой карандашей, питание от USB Зеленая

Настольная гибкая лама многофункциональная, изготовленная из матового ABS пластика. Оснащена настольная лампа встроенной точилкой для карандашей, которая имеет подсветку в режиме ночника. Питание лампы происходит через кабель micro USB-USB. Так же вы можете установить на подставку свой смартфон для просмотра видео либо канцелярские принадлежности.

На корпусе имеются органайзер для ручек и других небольших предметов, отсек-подставка для телефона. Так же, милый дизайн, который впишется в любой интерьер. В комплект входит micro-USB и USB шнур.

Характеристики:


	Материал: ABS пластик;
	Тип лампы: Светодиодная
	Управление: переключатель на задней стороне корпуса
	Кнопка включения на корпусе: Есть;
	Питание: USB
	Зарядка: вход micro USB
	Вес : 160 грамм.


Комплектация:


	Лампа LED;
	Кабель питания USB-micro USB;
	Фирменная коробка.

</description>
        <param name="Материал каркаса">пластик</param>
        <param name="Тип">Настольная лампа</param>
        <param name="Цвет">Зелёный</param>
        <param name="Состояние">Новое</param>
        <param name="Тип крепления">На поверхность</param>
        <param name="Тип лампы">Светодиодная</param>
      </offer>
      <offer id="1744062137" available="true">
        <url>https://aveon.net.ua/p1744062137-komplekt-makita-drel.html</url>
        <oldprice>3135</oldprice>
        <price>2985</price>
        <currencyId>UAH</currencyId>
        <categoryId>30018536</categoryId>
        <picture>https://images.prom.ua/4188272722_komplekt-makita-3.jpg</picture>
        <picture>https://images.prom.ua/4188272725_komplekt-makita-3.jpg</picture>
        <picture>https://images.prom.ua/4188272721_komplekt-makita-3.jpg</picture>
        <picture>https://images.prom.ua/4188272724_komplekt-makita-3.jpg</picture>
        <picture>https://images.prom.ua/4188272726_komplekt-makita-3.jpg</picture>
        <picture>https://images.prom.ua/4188272723_komplekt-makita-3.jpg</picture>
        <pickup>false</pickup>
        <delivery>true</delivery>
        <name>Комплект Makita 3 в 1 Дрель, лобзик, Болгарка / Макита три в одном</name>
        <vendor>Makita</vendor>
        <vendorCode>1744062137</vendorCode>
        <country_of_origin>Китай</country_of_origin>
        <description>Характеристики и описание

Электролобзик Makita


	Мощность 750 Вт
	Длина рабочего хода 18 мм
	Частота холостого хода 500 - 3.100 мин-1
	Глубина распила (дерево) 65 мм
	Глубина распила (металл) 6 мм
	Максимальная глубина распила (алюминий)




Дрель ударная Makita



Электронная регулировка скорости сверления и количества ударов в минуту

Конструкция реверса продлевает срок службы угольных щеток, сохраняет мощность в режиме реверса

Конструкция корпуса дрели позволяет удобно держать ее одной рукой при выполнении сложных потолочных работ

Удобный большой курковой включатель с фиксацией во включенном положении

Резиновые вставки на корпусе и на задней рукоятке


	Мощность 710 Вт
	Число оборотов холостого хода 0 - 3300 мин-1
	Частота ударов
	0 - 44,800 мин-1
	Диаметр зажимного патрона
	1,5 - 13 мм
	Диаметр сверления (сталь) 13 мм
	Диаметр сверления (дерево) 30 мм
	Максимальный диаметр сверления - бетон 16 мм
	Уровень шума: звуковое давление 92 дБ(А)
	Уровень шума: звуковая мощность 103 дБ(А)
	Уроень вибрации: ударное сверление по бетону 19,0 м/сек²
	Уроень вибрации: cверление по металлу 2,5 м/сек²
	Размеры (Д х Ш х В) 303 x 72 x 222 мм
	Вес в соответствии с EPTA 2 кг


Болгарка Makita

Тщательно продуманная для длительной работы конструкция, высокие технические параметры и вполне приемлемая стоимость – вот на что в первую очередь стоит обратить внимание в модели УШМ Makita 9558HN. Предлагаемый электроинструмент оснащается 840-Вт двигателем, который характеризуется длительным сроком службы благодаря надежной защите от пыли и повышенных температур и позволяет развивать скорость рабочего диска 125 мм до 11000 об/мин. Среди дополнительных опций в Makita 9558HN предусмотрены функция блокировки кнопки включения и фиксатор шпинделя, призванный обеспечить быструю смену режущего элемента. Главными особенностями дополнительной рукоятки являются возможность установки в двух местах, с правой и с левой руки, и значительное снижение уровня вибрации.
</description>
        <param name="Потребляемая мощность" unit="Вт">750</param>
      </offer>
      <offer id="1746416797" available="true">
        <url>https://aveon.net.ua/p1746416797-nastolnaya-skladnaya-lampa.html</url>
        <oldprice>555</oldprice>
        <price>405</price>
        <currencyId>UAH</currencyId>
        <categoryId>70181491</categoryId>
        <picture>https://images.prom.ua/4194980862_nastolnaya-skladnaya-lampa.jpg</picture>
        <picture>https://images.prom.ua/4194980908_nastolnaya-skladnaya-lampa.jpg</picture>
        <picture>https://images.prom.ua/4194980915_nastolnaya-skladnaya-lampa.jpg</picture>
        <picture>https://images.prom.ua/4194980909_nastolnaya-skladnaya-lampa.jpg</picture>
        <picture>https://images.prom.ua/4194980905_nastolnaya-skladnaya-lampa.jpg</picture>
        <picture>https://images.prom.ua/4194980912_nastolnaya-skladnaya-lampa.jpg</picture>
        <picture>https://images.prom.ua/4194980906_nastolnaya-skladnaya-lampa.jpg</picture>
        <picture>https://images.prom.ua/4194980910_nastolnaya-skladnaya-lampa.jpg</picture>
        <picture>https://images.prom.ua/4194980907_nastolnaya-skladnaya-lampa.jpg</picture>
        <picture>https://images.prom.ua/4194980911_nastolnaya-skladnaya-lampa.jpg</picture>
        <pickup>false</pickup>
        <delivery>true</delivery>
        <name>Настольная складная лампа 24 LED, YT-666, Белая, Зеленая, Синяя / Настольный светодиодный светильник</name>
        <vendorCode>1746416797</vendorCode>
        <country_of_origin>Китай</country_of_origin>
        <description>Описание:

Современная лед лампа с аккумулятором из 24 энергосберегающих светодиодов последнего поколения предназначена для освещения Вашего рабочего места за компьютерным или письменным столом. Лампа имеет два режима работы: экономный и полный, включение и переключение режимов работы лампы осуществляется перемещением кнопки, которая находится на правой панели лампы.

Настольная лампа LED 666 достаточно легкая и в сложенном виде имеет не большие габариты и является мобильным устройством, её можно складывать и носить на небольшой сумке. Встроенный аккумулятор лампы позволяет легко перемещать её на рабочем столе. 



Характеристики:


	Тип: лед лампа на аккумуляторе / настольная лампа на аккумуляторе
	24 светодиода
	2 режима свечения
	Встроенный аккумулятор позволяет использовать фонарь до 10 часов непрерывной работы(аккумуляторная батарея 800 мАч)
	Низкое энергопотребление
	Время зарядки 3 часов
	Батарея выдерживает до 500 раз заряда и разряда
	Регулируемый угол освещения
	Работает от сети и аккумулятора


Комплектация:


	Светильник настольный YT-666
	USB кабель
	Упаковка

</description>
        <param name="Тип">Настольная лампа</param>
        <param name="Цвет">Белый</param>
        <param name="Тип выключателя">Кнопка на каркасе/корпусе</param>
        <param name="Состояние">Новое</param>
        <param name="Тип лампы">Светодиодная</param>
      </offer>
      <offer id="1753101628" available="true">
        <url>https://aveon.net.ua/p1753101628-moschnyj-fonar-prozhektor.html</url>
        <oldprice>990</oldprice>
        <price>840</price>
        <currencyId>UAH</currencyId>
        <categoryId>70181491</categoryId>
        <picture>https://images.prom.ua/4215886277_moschnyj-fonar-prozhektor-perenosnoj.jpg</picture>
        <picture>https://images.prom.ua/4215886278_moschnyj-fonar-prozhektor-perenosnoj.jpg</picture>
        <picture>https://images.prom.ua/4215886280_moschnyj-fonar-prozhektor-perenosnoj.jpg</picture>
        <picture>https://images.prom.ua/4215886283_moschnyj-fonar-prozhektor-perenosnoj.jpg</picture>
        <picture>https://images.prom.ua/4215886281_moschnyj-fonar-prozhektor-perenosnoj.jpg</picture>
        <pickup>false</pickup>
        <delivery>true</delivery>
        <name>Мощный фонарь-прожектор переносной LED Yajia YJ-2886 Black ручной</name>
        <vendorCode>1753101628</vendorCode>
        <description>Фонарь может использоваться практически везде: в быту, во время активного отдыха или выполнения различных работ, на рыбалке и охоте.

Для удобства фонарь оснащен ремнем для ношения на плече.

 

Характеристики:


	Корпус: пластик
	Источник света: 5W+22SMD-LED
	Количество режимов работы: 3 (высокий, средний, боковая панель)
	Источник питания: встроенный аккумулятор 5500 mAh
	Зарядка аккумулятора от сети 220V
	Дополнительные функции: USB power bank
	Размеры: комплект с коробкой – 20*15*11см, l=19,5см, d=10 см
	Вес: комплект с коробкой – 1050г, фонарик – 920г


 

Комплектация:


	фонарь YJ-2886
	зарядное устройство от сети 220V
	ремень
	коробка

</description>
        <param name="Тип питания">Аккумулятор</param>
        <param name="Состояние">Новое</param>
        <param name="Тип заряда">От сети</param>
        <param name="Тип лампы">Светодиодная</param>
        <param name="Тип фонаря">Ручной</param>
        <param name="Цвет">Черный</param>
      </offer>
      <offer id="1761704098" available="true">
        <url>https://aveon.net.ua/p1761704098-shvabra-vedrom-otzhimom.html</url>
        <oldprice>660</oldprice>
        <price>510</price>
        <currencyId>UAH</currencyId>
        <categoryId>30017053</categoryId>
        <picture>https://images.prom.ua/4244888683_shvabra-s-vedrom.jpg</picture>
        <picture>https://images.prom.ua/4244888687_shvabra-s-vedrom.jpg</picture>
        <picture>https://images.prom.ua/4244888686_shvabra-s-vedrom.jpg</picture>
        <picture>https://images.prom.ua/4244888679_shvabra-s-vedrom.jpg</picture>
        <picture>https://images.prom.ua/4244888682_shvabra-s-vedrom.jpg</picture>
        <picture>https://images.prom.ua/4244888685_shvabra-s-vedrom.jpg</picture>
        <picture>https://images.prom.ua/4244888684_shvabra-s-vedrom.jpg</picture>
        <pickup>false</pickup>
        <delivery>true</delivery>
        <name>Швабра с ведром и отжимом| Швабра с отжимом и ведром лентяйка YT-200</name>
        <vendorCode>1761704098</vendorCode>
        <country_of_origin>Китай</country_of_origin>
        <description>ОПИСАНИЕ

Швабра с ведром Scratch Cleaning Easy Mop с автоматическим Швабра с отжимом ведром комплект Scratch Cleaning Easy Mop с автоматическим отжимом и складной ручкой Мытье полов вызывает у Вас раздражение и нежелание убирать? Комплект для уборки EasyMop – простое решение для всех бытовых проблем. Никаких разводов и лишней воды. Идеально чистый пол в считанные минуты. Чтобы добраться до труднодоступных участков, можно двигать мебель.



Ведро оснащено системой полоскания и отжима, позволяет полностью удалять грязь из насадок.

Антибактериальная сушка в вертикальном положении избавит вас от вредных бактерий. Благодаря ведру со специальной крышкой вы с легкостью вымоете и выжмете тряпку, не прикасаясь к ней руками и не снимая ее со швабры.


	В комплект входят две насадки швабры из микрофибры.
	Комфортная конструкция.
	Благодаря продуманной конструкции и компактным размерам комплект займет минимум места, но только обычная швабра!
	Ручка с регулируемой длиной состоит из нескольких частей, которые легко собрать и разобрать. В разобранном состоянии швабра занимает меньше места.
	Инструмент выполнен из металла и прочного пластика и прослужит вам долго. для уборки в тяжелодоступных местах.
	Подвижная головка швабры позволит вымыть пол под кроватью, шкафом или во втором труднодоступном месте.
	Отлично подходит для линолеума, деревянных полов, ламинатов, полов из плитки и других поверхностей.






Характерисктика:


	система отжима самоочищающееся ведро
	Легко проходит под мебелью.
	Хорошо удаляет шерсть животных и волосы. Воспользоваться комплектом для уборки EasyMop очень просто
	Характеристики : Размеры ведра: 370х210х180 мм
	Объем ведра 8 литров Материал ручки и ведра металл, пластик ABS.

</description>
        <param name="Тип ручки">разборная</param>
        <param name="Основное назначение">Универсальное</param>
        <param name="Комплектация ведром">Есть (с отжимом)</param>
        <param name="Наличие механизма отжима">Есть</param>
        <param name="Тип">Ручка</param>
      </offer>
    </offers>
  </shop>
</yml_catalog>